Workbook

Sheet Resumen Ejecutivo
B2: RESUMEN EJECUTIVO COMPARATIVO — RECICLADORAS POR GIRO — SAN LUIS POTOSÍ
B3: Modelo financiero CFO — Cinco giros × Tres escenarios (40% base)
C4: PET | D4: Papel/Cartón | E4: Aluminio | F4: Vidrio | G4: Orgánicos
B5: INVERSIÓN
B6: CAPEX total | C6: =PET!C64 -> 3840994.8 | D6: ='Papel-Carton'!C63 -> 3396733.8 | E6: =Aluminio!C64 -> 3865004.5 | F6: =Vidrio!C64 -> 1872563.9 | G6: ='Organicos-Composta'!C69 -> 3204959.2
B7: Capital de trabajo | C7: =PET!C63 -> 1514994.8 | D7: ='Papel-Carton'!C62 -> 1517733.8 | E7: =Aluminio!C63 -> 1711204.5 | F7: =Vidrio!C63 -> 562563.94 | G7: ='Organicos-Composta'!C68 -> 991159.18
B8: Inversión total | C8: =PET!C64 -> 3840994.8 | D8: ='Papel-Carton'!C63 -> 3396733.8 | E8: =Aluminio!C64 -> 3865004.5 | F8: =Vidrio!C64 -> 1872563.9 | G8: ='Organicos-Composta'!C69 -> 3204959.2
B9: Estructura D/E | C9: =PET!C29 -> 0.6 | D9: ='Papel-Carton'!C29 -> 0.6 | E9: =Aluminio!C29 -> 0.6 | F9: =Vidrio!C29 -> 0.6 | G9: ='Organicos-Composta'!C29 -> 0.6
B10: Capital propio requerido | C10: =PET!C288 -> 1536397.9 | D10: ='Papel-Carton'!C295 -> 1358693.5 | E10: =Aluminio!C288 -> 1546001.8 | F10: =Vidrio!C287 -> 749025.57 | G10: ='Organicos-Composta'!C296 -> 1281983.7
B12: RENTABILIDAD (Escenario 40% base)
B13: Ingreso mensual Año 1 | C13: =PET!D286 -> 2140810.6 | D13: ='Papel-Carton'!D293 -> 2037934.1 | E13: =Aluminio!D286 -> 2401137 | F13: =Vidrio!D285 -> 475099.91 | G13: ='Organicos-Composta'!D294 -> 274975.2
B14: Ingreso mensual Año 3 | C14: =PET!D287 -> 4281621.1 | D14: ='Papel-Carton'!D294 -> 4075868.2 | E14: =Aluminio!D287 -> 4802274.1 | F14: =Vidrio!D286 -> 950199.83 | G14: ='Organicos-Composta'!D295 -> 549950.4
B15: EBITDA Año 3 | C15: =PET!D280 -> 9956876.5 | D15: ='Papel-Carton'!D287 -> 612975.08 | E15: =Aluminio!D280 -> 10077626 | F15: =Vidrio!D279 -> -1770745.7 | G15: ='Organicos-Composta'!D288 -> 1070928.1
B16: Margen EBITDA Año 3 % | C16: =PET!D281 -> 0.19379102 | D16: ='Papel-Carton'!D288 -> 0.012532608 | E16: =Aluminio!D281 -> 0.17487593 | F16: =Vidrio!D280 -> -0.1552959 | G16: ='Organicos-Composta'!D289 -> 0.16227647
B17: VPN a WACC | C17: =PET!D274 -> 28539880 | D17: ='Papel-Carton'!D281 -> -4449205.3 | E17: =Aluminio!D274 -> 28742303 | F17: =Vidrio!D273 -> -9774471.3 | G17: ='Organicos-Composta'!D282 -> -1982824.8
B18: TIR proyecto | C18: =PET!D275 -> 1.1288502 | D18: ='Papel-Carton'!D282 -> -0.067991804 | E18: =Aluminio!D275 -> 1.1032428 | F18: =Vidrio!D274 -> - | G18: ='Organicos-Composta'!D283 -> 0.08151614
B19: TIR equity | C19: =PET!D276 -> 1.1288502 | D19: ='Papel-Carton'!D283 -> -0.067991804 | E19: =Aluminio!D276 -> 1.1032428 | F19: =Vidrio!D275 -> - | G19: ='Organicos-Composta'!D284 -> 0.08151614
B20: Payback simple (meses) | C20: =PET!D277 -> 15.005511 | D20: ='Papel-Carton'!D284 -> 999 | E20: =Aluminio!D277 -> 15.420765 | F20: =Vidrio!D276 -> 999 | G20: ='Organicos-Composta'!D285 -> 999
B21: Payback descontado (meses) | C21: =PET!D278 -> 17.256337 | D21: ='Papel-Carton'!D285 -> 1148.85 | E21: =Aluminio!D278 -> 17.73388 | F21: =Vidrio!D277 -> 1148.85 | G21: ='Organicos-Composta'!D286 -> 1148.85
B22: MOIC | C22: =PET!D279 -> 16.562315 | D22: ='Papel-Carton'!D286 -> 0.54309141 | E22: =Aluminio!D279 -> 16.104723 | F22: =Vidrio!D278 -> -7.4056923 | G22: ='Organicos-Composta'!D287 -> 1.6859638
B24: RIESGO
B25: DSCR mínimo | C25: =PET!D282 -> 7.1609531 | D25: ='Papel-Carton'!D289 -> 0.49850869 | E25: =Aluminio!D282 -> 7.2027715 | F25: =Vidrio!D281 -> -2.6122273 | G25: ='Organicos-Composta'!D290 -> 0.92305853
B26: Break-even kg/día | C26: =PET!D283 -> 43883.567 | D26: ='Papel-Carton'!D290 -> 143332.87 | E26: =Aluminio!D283 -> 18863.525 | F26: =Vidrio!D282 -> 41923.378 | G26: ='Organicos-Composta'!D291 -> 12130.237
B27: Margen de seguridad | C27: =PET!D284 -> 1.2403732 | D27: ='Papel-Carton'!D291 -> 1.0126917 | E27: =Aluminio!D284 -> 1.2119389 | F27: =Vidrio!D283 -> 0.86557911 | G27: ='Organicos-Composta'!D292 -> 1.1937112
B28: Escenario pesimista 50% captura | C28: =PET!E94*0.5-PET!C79 -> -1311070.9 | D28: ='Papel-Carton'!E93*0.5-'Papel-Carton'!C79 -> -1986852.8 | E28: =Aluminio!E94*0.5-Aluminio!C80 -> -1561334.9 | F28: =Vidrio!E93*0.5-Vidrio!C79 -> -622662.05 | G28: ='Organicos-Composta'!E102*0.5-'Organicos-Composta'!C84 -> -185731.19
B30: TABLA COMPARATIVA POR ESCENARIO × GIRO
C31: PET - | F31: Papel/Cartón | I31: Aluminio | L31: Vidrio | O31: Orgánicos
B32: Métrica | C32: Esc_municipal | D32: Esc_concesionario | E32: Esc_impacto | F32: Esc_municipal | G32: Esc_concesionario | H32: Esc_impacto | I32: Esc_municipal | J32: Esc_concesionario | K32: Esc_impacto | L32: Esc_municipal | M32: Esc_concesionario | N32: Esc_impacto | O32: Esc_municipal | P32: Esc_concesionario | Q32: Esc_impacto
B33: Volumen procesado t/mes | C33: =PET!D86 -> 122.472 | D33: =PET!E86 -> 217.728 | E33: =PET!F86 -> 870.912 | F33: ='Papel-Carton'!D85 -> 326.592 | G33: ='Papel-Carton'!E85 -> 580.608 | H33: ='Papel-Carton'!F85 -> 2322.432 | I33: =Aluminio!D86 -> 51.43824 | J33: =Aluminio!E86 -> 91.44576 | K33: =Aluminio!F86 -> 365.78304 | L33: =Vidrio!D85 -> 81.648 | M33: =Vidrio!E85 -> 145.152 | N33: =Vidrio!F85 -> 580.608 | O33: ='Organicos-Composta'!D90 -> 108.6 | P33: ='Organicos-Composta'!E90 -> 144.8 | Q33: ='Organicos-Composta'!F90 -> 289.6
B34: Ingreso mensual MXN | C34: =PET!D94 -> 2913608.9 | D34: =PET!E94 -> 4281621.1 | E34: =PET!F94 -> 11737716 | F34: ='Papel-Carton'!D93 -> 2905035.8 | G34: ='Papel-Carton'!E93 -> 4075868.2 | H34: ='Papel-Carton'!F93 -> 9771632.6 | I34: =Aluminio!D94 -> 3283817.2 | J34: =Aluminio!E94 -> 4802274.1 | K34: =Aluminio!F94 -> 12995357 | L34: =Vidrio!D93 -> 687577.4 | M34: =Vidrio!E93 -> 950199.83 | N34: =Vidrio!F93 -> 2167839.3 | O34: ='Organicos-Composta'!D102 -> 493912.8 | P34: ='Organicos-Composta'!E102 -> 549950.4 | Q34: ='Organicos-Composta'!F102 -> 774100.8
B35: EBITDA mensual | C35: =PET!D94-PET!C79 -> -538272.53 | D35: =PET!E94-PET!C79 -> 829739.71 | E35: =PET!F94-PET!C79 -> 8285835.1 | F35: ='Papel-Carton'!D93-'Papel-Carton'!C79 -> -1119751.1 | G35: ='Papel-Carton'!E93-'Papel-Carton'!C79 -> 51081.257 | H35: ='Papel-Carton'!F93-'Papel-Carton'!C79 -> 5746845.7 | I35: =Aluminio!D94-Aluminio!C80 -> -678654.72 | J35: =Aluminio!E94-Aluminio!C80 -> 839802.13 | K35: =Aluminio!F94-Aluminio!C80 -> 9032885 | L35: =Vidrio!D93-Vidrio!C79 -> -410184.57 | M35: =Vidrio!E93-Vidrio!C79 -> -147562.14 | N35: =Vidrio!F93-Vidrio!C79 -> 1070077.3 | O35: ='Organicos-Composta'!D102-'Organicos-Composta'!C84 -> 33206.408 | P35: ='Organicos-Composta'!E102-'Organicos-Composta'!C84 -> 89244.008 | Q35: ='Organicos-Composta'!F102-'Organicos-Composta'!C84 -> 313394.41
B36: Meses a break-even | C36: =PET!C277 -> 23.0422 | D36: =PET!D277 -> 15.005511 | E36: =PET!E277 -> 1.9003665 | F36: ='Papel-Carton'!C284 -> 999 | G36: ='Papel-Carton'!D284 -> 999 | H36: ='Papel-Carton'!E284 -> 1.7413674 | I36: =Aluminio!C277 -> 999 | J36: =Aluminio!D277 -> 15.420765 | K36: =Aluminio!E277 -> 1.2507912 | L36: =Vidrio!C276 -> 999 | M36: =Vidrio!D276 -> 999 | N36: =Vidrio!E276 -> 4.8049643 | O36: ='Organicos-Composta'!C285 -> 999 | P36: ='Organicos-Composta'!D285 -> 999 | Q36: ='Organicos-Composta'!E285 -> 38.725392
B37: TIR | C37: =PET!C275 -> 0.80546726 | D37: =PET!D275 -> 1.1288502 | E37: =PET!E275 -> 6.7831833 | F37: ='Papel-Carton'!C282 -> - | G37: ='Papel-Carton'!D282 -> -0.067991804 | H37: ='Papel-Carton'!E282 -> 7.3620998 | I37: =Aluminio!C275 -> - | J37: =Aluminio!D275 -> 1.1032428 | K37: =Aluminio!E275 -> 10.073352 | L37: =Vidrio!C274 -> - | M37: =Vidrio!D274 -> - | N37: =Vidrio!E274 -> 2.922723 | O37: ='Organicos-Composta'!C283 -> -0.12700653 | P37: ='Organicos-Composta'!D283 -> 0.08151614 | Q37: ='Organicos-Composta'!E283 -> 0.55790307
B38: MOIC | C38: =PET!C279 -> 8.8950849 | D38: =PET!D279 -> 16.562315 | E38: =PET!E279 -> 118.58732 | F38: ='Papel-Carton'!C286 -> -25.901764 | G38: ='Papel-Carton'!D286 -> 0.54309141 | H38: ='Papel-Carton'!E286 -> 129.18975 | I38: =Aluminio!C279 -> -14.121674 | J38: =Aluminio!D279 -> 16.104723 | K38: =Aluminio!E279 -> 179.19621 | L38: =Vidrio!C278 -> -19.376764 | M38: =Vidrio!D278 -> -7.4056923 | N38: =Vidrio!E278 -> 48.097751 | O38: ='Organicos-Composta'!C287 -> 0.20360004 | P38: ='Organicos-Composta'!D287 -> 1.6859638 | Q38: ='Organicos-Composta'!E287 -> 7.6154186
B40: Nota: 30% = escenario municipio | 40% = negociación concesionario | 80% = fondos de impacto
B41: Generado: 2026-03-26 21:26 | Actualizada: 2026-04-10 16:00 | Modelo Recicladoras por Giro — Capítulo SLP
B44: DESGLOSE DE REVENUE POR ACTIVIDAD — Escenario 40% base (MXN/mes)
B45: Métrica | C45: PET | D45: Papel/Cartón | E45: Aluminio | F45: Vidrio | G45: Orgánicos
A46: Ingreso Recicladora (valor agregado) | B46: =PET!E88 -> 2961100.8 | C46: =PET!E88 -> 2961100.8 | D46: ='Papel-Carton'!E87 -> 2351462.4 | E46: =Aluminio!E88 -> 3264613.6 | F46: =Vidrio!E87 -> 511457.59 | G46: ='Organicos-Composta'!E96 -> 393856
B47: Ingreso Centro de Acopio (comercialización) | C47: =PET!E91 -> 1796256 | D47: ='Papel-Carton'!E90 -> 2177280 | E47: =Aluminio!E91 -> 2071246.5 | F47: =Vidrio!E90 -> 544320 | G47: ='Organicos-Composta'!E99 -> 217200
A48: Ingreso Total Bruto (Recicladora + Acopio) | B48: =C46+C47 -> 4757356.8 | C48: =C46+C47 -> 4757356.8 | D48: =D46+D47 -> 4528742.4 | E48: =E46+E47 -> 5335860.1 | F48: =F46+F47 -> 1055777.6 | G48: =G46+G47 -> 611056
B49: % Revenue Recicladora | C49: =C46/C48 -> 0.62242563 | D49: =D46/D48 -> 0.51923077 | E49: =E46/E48 -> 0.61182519 | F49: =F46/F48 -> 0.48443687 | G49: =G46/G48 -> 0.64454976
B50: % Revenue Centro de Acopio | C50: =C47/C48 -> 0.37757437 | D50: =D47/D48 -> 0.48076923 | E50: =E47/E48 -> 0.38817481 | F50: =F47/F48 -> 0.51556313 | G50: =G47/G48 -> 0.35545024
B51: (–) CMV Compra MP (centros de acopio) | C51: =-PET!C68 -> -2694384 | D51: =-'Papel-Carton'!C67 -> -3265920 | E51: =-Aluminio!C68 -> -3106869.7 | F51: =-Vidrio!C68 -> -816480 | G51: =-'Organicos-Composta'!C73 -> -130320
B52: Margen Bruto (Ingreso Neto – CMV) | C52: =PET!E94-PET!C68 -> 1587237.1 | D52: ='Papel-Carton'!E93-'Papel-Carton'!C67 -> 809948.16 | E52: =Aluminio!E94-Aluminio!C68 -> 1695404.4 | F52: =Vidrio!E93-Vidrio!C68 -> 133719.83 | G52: ='Organicos-Composta'!E102-'Organicos-Composta'!C73 -> 419630.4
B53: % Margen Bruto s/Ingreso Neto | C53: =C52/PET!E94 -> 0.37070938 | D53: =D52/'Papel-Carton'!E93 -> 0.19871795 | E53: =E52/Aluminio!E94 -> 0.35304199 | F53: =F52/Vidrio!E93 -> 0.14072811 | G53: =G52/'Organicos-Composta'!E102 -> 0.76303318

Sheet Matriz_Compradores


A1: MATRIZ DE COMPRADORES — ECOSISTEMA RSU ZM SLP
A3: SECCIÓN 1 — BLOQUE MAESTRO DE PRECIOS (VERDAD ÚNICA)
A5: Material | B5: Precio_MXN_kg | C5: Fuente | D5: Fecha_referencia | E5: Notas
A6: PET | B6: 5.50 | C6: MB Sección 9 | D6: 2024 | E6: Precio piso recicladora
A7: Papel/Cartón | B7: 2.50 | C7: MB Sección 9 | D7: 2024 | E7: Precio piso recicladora
A8: Vidrio | B8: 1.30 | C8: MB Sección 9 | D8: 2024 | E8: Precio piso recicladora
A9: Aluminio | B9: 46310 | C9: MB Sección 9 | D9: 2024 | E9: Precio piso recicladora
A10: Orgánicos/Composta | B10: 0.80 | C10: MB Sección 9 | D10: 2024 | E10: Estimado composta
A12: SECCIÓN 2 — COMPRADORES ANCLA Y CAPACIDADES
A14: Comprador | B14: Giro | C14: Material_principal | D14: Capacidad_t_mes | E14: Precio_oferta_MXN_kg | F14: Contacto_referencia
A15: Grupo Diarq | B15: Recicladora PET | C15: PET | D15: 300 | E15: 5.50 | F15: Por confirmar
A16: Papelera Moctezuma | B16: Recicladora Papel | C16: Papel/Cartón | D16: 500 | E16: 2.50 | F16: Por confirmar
A17: Vitro / Owens | B17: Recicladora Vidrio | C17: Vidrio | D17: 200 | E17: 1.30 | F17: Por confirmar
A18: Aluminio del Norte | B18: Recicladora Aluminio | C18: Aluminio | D18: 50 | E18: 46310 | F18: Por confirmar
A19: Biocompostaje SLP | B19: Compostador | C19: Orgánicos | D19: 400 | E19: 0.80 | F19: Por confirmar
A21: SECCIÓN 3 — OFERTA POR FASE
A23: Fase | B23: Cobertura_viviendas_% | C23: RSU_t_dia | D23: PET_t_dia | E23: Papel_t_dia | F23: Vidrio_t_dia | G23: Aluminio_t_dia | H23: Organicos_t_dia
A24: 1 | B24: 0.25 | C24: 201.60 | D24: 46307 | E24: 36.29 | F24: 46212 | G24: 6.35 | H24: 138.00
A25: 2 | B25: 0.6 | C25: 483.84 | D25: 46110 | E25: 87.09 | F25: 21.77 | G25: 15.24 | H25: 331.20
A26: 3 | B26: 1 | C26: 806.40 | D26: 48.38 | E26: 145.15 | F26: 36.29 | G26: 25.40 | H26: 552.00
A28: SECCIÓN 4 — HALLAZGOS Y COMPATIBILIDAD
A30: Hallazgo | B30: Detalle | C30: Estatus
A31: Precios EST vs MB | B31: Precios en hoja EST coinciden con MB Sección 9 | C31: VERIFICADO ✓
A32: Precios CAP vs MB | B32: Precios en hoja CAP coinciden con MB Sección 9 | C32: VERIFICADO ✓
A33: Capacidad compradores Fase 1 | B33: Oferta PET 12.1 t/día < Capacidad Diarq 300 t/mes (~10 t/día): compatible | C33: COMPATIBLE ✓
A34: Capacidad compradores Fase 3 | B34: Oferta PET 48.4 t/día > Capacidad ancla actual: requiere 2do comprador | C34: ATENCIÓN ⚠
A35: Vidrio Fase 3 | B35: Oferta 36.3 t/día > Capacidad Vitro/Owens estimada: requiere negociación | C35: ATENCIÓN ⚠
A36: Orgánicos | B36: Mercado composta local en desarrollo; precio 0.80 MXN/kg estimado | C36: POR CONFIRMAR
A37: Discrepancias precios | B37: Cero discrepancias detectadas entre EST, CAP y MB | C37: VERIFICADO ✓

Sheet Dimensionamiento_sistema
A1: MIX ESCALONADO DE RECICLADORAS
A3: Fraccion | B3: % Flujo | C3: t/dia bruto | D3: t/dia neto (post 10%) | E3: t/ano neto | F3: Demanda existente t/ano | G3: GAP t/ano | H3: Nuevas recicladoras necesarias
A4: Organicos | B4: 0.45 | C4: 326.6 | D4: 293.9 | E4: 88179 | F4: 0 | G4: 88179 | H4: Planta composta + biodigestor
A5: Papel/Carton | B5: 0.2 | C5: 145.2 | D5: 130.6 | E5: 39190 | F5: 79200 | G5: 0 | H5: Cubierto por IPSL (79,200 t/a)
A6: PET | B6: 0.15 | C6: 108.9 | D6: 98.0 | E6: 29393 | F6: 5700 | G6: 23693 | H6: 1-2 plantas PET nuevas
A7: Vidrio | B7: 0.05 | C7: 36.3 | D7: 32.7 | E7: 9798 | F7: 0 | G7: 9798 | H7: 1 planta procesamiento vidrio
A8: Aluminio | B8: 0.05 | C8: 36.3 | D8: 32.7 | E8: 9798 | F8: 0 | G8: 9798 | H8: 1 planta fundicion aluminio
A9: Otros (no valorizable) | B9: 0.1 | C9: 72.6 | H9: Disposicion final
A11: TOTAL | B11: 1 | C11: 725.8 | D11: 588.2 | E11: 176358 | F11: 84900 | G11: 131468
A13: ESCALONAMIENTO POR FASE DE COBERTURA
A15: Fraccion | B15: FASE A (25%) t/ano capturado | C15: Demanda existente | D15: GAP A | E15: Recicladoras nuevas A | F15: FASE B (60%) t/ano capturado | G15: GAP B | H15: Recicladoras nuevas B | I15: FASE C (100%) t/ano capturado | J15: GAP C | K15: Recicladoras nuevas C
A16: Organicos | B16: 22045 | C16: 0 | D16: 22045 | E16: 1 | F16: 52907 | G16: 52907 | H16: 2 | I16: 88179 | J16: 88179 | K16: 3
A17: Papel/Carton | B17: 9798 | C17: 79200 | D17: 0 | E17: 0 | F17: 23515 | G17: 0 | H17: 0 | I17: 39190 | J17: 0 | K17: 0
A18: PET | B18: 7348 | C18: 5700 | D18: 1648 | E18: 1 | F18: 17636 | G18: 11936 | H18: 1 | I18: 29393 | J18: 23693 | K18: 2
A19: Vidrio | B19: 2450 | C19: 0 | D19: 2450 | E19: 1 | F19: 5879 | G19: 5879 | H19: 1 | I19: 9798 | J19: 9798 | K19: 2
A20: Aluminio | B20: 2450 | C20: 0 | D20: 2450 | E20: 1 | F20: 5879 | G20: 5879 | H20: 1 | I20: 9798 | J20: 9798 | K20: 2
A22: TOTAL RECICLADORAS | E22: 4 | H22: 4 | K22: 9
A25: SECCIÓN 3 — CAPEX/OPEX AGREGADO POR FASE
A27: Fracción | B27: CAPEX unitario | C27: Recicladoras Fase A | D27: CAPEX Fase A | E27: Recicladoras Fase C | F27: CAPEX Fase C
A28: Orgánicos | B28: 3204959 | C28: 1 | D28: =B28*C28 -> 3204959 | E28: 1 | F28: =B28*E28 -> 3204959
A29: PET | B29: 3840995 | C29: 1 | D29: =B29*C29 -> 3840995 | E29: 1 | F29: =B29*E29 -> 3840995
A30: Vidrio | B30: 1872564 | C30: 1 | D30: =B30*C30 -> 1872564 | E30: 2 | F30: =B30*E30 -> 3745128
A31: Aluminio | B31: 3865005 | C31: 1 | D31: =B31*C31 -> 3865005 | E31: 2 | F31: =B31*E31 -> 7730010
A32: Papel/Cartón | B32: 3396734 | C32: 0 | D32: =B32*C32 -> 0 | E32: 0 | F32: =B32*E32 -> 0
A33: TOTAL | C33: =SUM(C28:C32) -> 4 | D33: =SUM(D28:D32) -> 12783523 | E33: =SUM(E28:E32) -> 6 | F33: =SUM(F28:F32) -> 18521092
A36: PROYECCIÓN EMPLEO AGREGADO
A38: Giro | B38: Empleos por planta | C38: Plantas Fase A | D38: Empleos Fase A | E38: Plantas Fase C | F38: Empleos Fase C
A39: Orgánicos | B39: 20 | C39: 1 | D39: =B39*C39 -> 20 | E39: 1 | F39: =B39*E39 -> 20
A40: PET | B40: 20 | C40: 1 | D40: =B40*C40 -> 20 | E40: 1 | F40: =B40*E40 -> 20
A41: Vidrio | B41: 20 | C41: 1 | D41: =B41*C41 -> 20 | E41: 2 | F41: =B41*E41 -> 40
A42: Aluminio | B42: 20 | C42: 1 | D42: =B42*C42 -> 20 | E42: 2 | F42: =B42*E42 -> 40
A43: Papel/Cartón | B43: 20 | C43: 0 | D43: =B43*C43 -> 0 | E43: 0 | F43: =B43*E43 -> 0
A44: TOTAL | C44: =SUM(C39:C43) -> 4 | D44: =SUM(D39:D43) -> 80 | E44: =SUM(E39:E43) -> 6 | F44: =SUM(F39:F43) -> 120
A46: Factor multiplicador indirecto: 2.5x-3.5x

Sheet Datos para Gráficas
A1: TABLA 1 — TIR POR GIRO (Escenario 40% base)Giro | B1: TIR %
A3: PET | B3: 112.9%
A4: Papel/Cartón | B4: -6.8%
A5: Aluminio | B5: 110.3%
A6: Vidrio | B6: No viable
A7: Orgánicos | B7: 8.2%
A10: TABLA 2 — PAYBACK POR GIRO (Escenario 40%)Giro | B10: Payback (meses)
A12: PET | B12: 15.0
A13: Papel/Cartón | B13: 999.0
A14: Aluminio | B14: 46127
A15: Vidrio | B15: 999.0
A16: Orgánicos | B16: 999.0
A19: TABLA 3 — EBITDA POR GIRO (Año 3, Escenario 40%)Giro | B19: EBITDA Anual (MXN) | C19: Margen %
A21: PET | B21: 9956877 | C21: 19.4%
A22: Papel/Cartón | B22: 612975 | C22: 1.3%
A23: Aluminio | B23: 10077626 | C23: 17.5%
A24: Vidrio | B24: -1770746 | C24: -15.5%
A25: Orgánicos | B25: 1070928 | C25: 16.2%
A28: TABLA 4 — VOLUMEN PROCESADO POR ESCENARIO (t/mes)Giro | B28: 0.3 | C28: 0.4 | D28: 0.8
A30: PET | B30: 122.5 | C30: 217.7 | D30: 870.9
A31: Papel/Cartón | B31: 326.6 | C31: 580.6 | D31: 154224
A32: Aluminio | B32: 51.4 | C32: 91.4 | D32: 365.8
A33: Vidrio | B33: 81.6 | C33: 145.2 | D33: 580.6
A34: Orgánicos | B34: 108.6 | C34: 144.8 | D34: 289.6
A37: TABLA 5 — CAPEX POR GIRO (MXN)Giro | B37: CAPEX Total (MXN)
A39: PET | B39: 3840995
A40: Papel/Cartón | B40: 3396734
A41: Aluminio | B41: 3865005
A42: Vidrio | B42: 1872564
A43: Orgánicos | B43: 3204959
A46: TABLA 6 — COMPOSICIÓN OPEX POR GIRO (Esc 40% mensual, sin CMV, MXN/mes)Giro | B46: Nómina | C46: Energía | D46: Agua/Servicios | E46: Insumos/Químicos | F46: Consumibles | G46: Flete | H46: Mantenimiento | I46: TOTAL
A48: PET | B48: 116775 | C48: 79424 | D48: 4500 | E48: 128449 | F48: 8000 | G48: 380589 | H48: 4315 | I48: 722052
A49: Papel/Cartón | B49: 175500 | C49: 20315 | D49: 4500 | E49: 122276 | F49: 6000 | G49: 362299 | H49: 3217 | I49: 694107
A50: Aluminio | B50: 107325 | C50: 136172 | D50: 3500 | E50: 144068 | F50: 5000 | G50: 426869 | H50: 3560 | I50: 826494
A51: Vidrio | B51: 104625 | C51: 19510 | D51: 3000 | E51: 28506 | F51: 4000 | G51: 84462 | H51: 2156 | I51: 246259
A52: Orgánicos | B52: 186975 | C52: 18506 | D52: 6000 | E52: 16499 | F52: 3000 | G52: 48884 | H52: 3623 | I52: 283487
A55: TABLA 7 — REVE | B55: Revenue por Actividad (MXN/mes, Escenario 40%)
B57: Ingreso Recicladora | C57: Ingreso Centro de Acopio | D57: Ingreso Total Bruto | E57: CMV Compra MP | F57: Margen Bruto
A58: PET | B58: 2961101 | C58: 1796256 | D58: 4757357 | E58: -2694384 | F58: 1587237
A59: Papel/Cartón | B59: 2351462 | C59: 2177280 | D59: 4528742 | E59: -3265920 | F59: 809948
A60: Aluminio | B60: 3264614 | C60: 2071246 | D60: 5335860 | E60: -3106870 | F60: 1695404
A61: Vidrio | B61: 511458 | C61: 544320 | D61: 1055778 | E61: -816480 | F61: 133720
A62: Orgánicos | B62: 393856 | C62: 217200 | D62: 611056 | E62: -130320 | F62: 419630

Sheet PET
A1: 26
B2: BLOQUE A — SUPUESTOS PARAMETRIZADOS — PET
B3: Parámetro | C3: Valor | D3: Unidad | E3: Fuente / Nota
B4: Tipo de cambio USD/MXN | C4: 17.1 | D4: MXN/USD
B5: Tarifa eléctrica industrial SLP | C5: 3 | D5: MXN/kWh | E5: Ref CFE tarifa GDMTH SLP
B6: Precio gas LP industrial | C6: 18.5 | D6: MXN/kg | E6: Supuesto razonado
B7: Precio diésel | C7: 26 | D7: MXN/litro | E7: Supuesto razonado
B8: Factor contingencia energética | C8: 1.1 | D8: x
B9: Días operativos/año | C9: 300 | D9: días
B10: Días operativos/mes | C10: 25 | D10: días
B11: Merma estimada | C11: 0.1 | D11: % | E11: Teorico
B12: Renta zona industrial | C12: 65 | D12: MXN/m²/mes | E12: teorico
B13: Factor prestaciones sociales | C13: 1.35 | D13: x | E13: teorico
B14: WACC | C14: 0.2 | D14: %
B15: ISR | C15: 0.3 | D15: %
B16: PTU | C16: 0.1 | D16: %
B17: Reserva legal | C17: 0.05 | D17: %
B18: Vida útil maquinaria industrial | C18: 10 | D18: años | E18: teorico
B19: Vida útil transporte | C19: 4 | D19: años
B20: Vida útil cómputo | C20: 3 | D20: años
B21: Factor utilización equipos proceso | C21: 0.75 | D21: %
B22: Capacidad arranque Año 1 | C22: 0.5 | D22: %
B23: Capacidad arranque Año 2 | C23: 0.75 | D23: %
B24: Capacidad arranque Año 3+ | C24: 1 | D24: %
B25: DSO (días cuentas por cobrar) | C25: 30 | D25: días
B26: DIO (días inventario) | C26: 7 | D26: días
B27: DPO (días cuentas por pagar) | C27: 15 | D27: días
B28: Múltiplo valor terminal EBITDA | C28: 5 | D28: x | E28: Rango 4-6x
B29: Estructura D/E (% deuda) | C29: 0.6 | D29: % | E29: 60/40
B30: Tasa interés deuda | C30: 0.135 | D30: % anual
B31: Plazo deuda | C31: 6 | D31: años
B33: Parámetros específicos — PET
B34: Volumen entrada t/mes | C34: 1360.8 | D34: t/mes | E34: Supuesto razonado
B35: Escenario % procesado 30% | C35: 0.3 | D35: % | E35: 30%=municipio
B36: Escenario % procesado 40% | C36: 0.4 | D36: % | E36: 40%=concesionario
B37: Escenario % procesado 80% | C37: 0.8 | D37: % | E37: 80%=fondos de impacto
B38: Rendimiento proceso kg/kg entrada | C38: 0.85 | D38: kg/kg
B39: Precio PET procesado | C39: 16 | D39: MXN/kg | E39: Valor agregado
B40: Precio compra MP centros de acopio (PET) | C40: 5.5 | D40: MXN/kg | E40: Precio compra en centros de acopio
B41: Nave industrial m² | C41: 300 | D41: m²
B42: Nómina mensual (6 operarios + 1 supervisor + 1 técnico proceso) | C42: 116775 | D42: MXN/mes | E42: (6*10000+1*17500+1*20000)*1.35
B43: Compradores ancla | C43: ALPLA Monterrey, FEMSA Reciclaje, Industrias Rebermex | E43: Condiciones mínimas pureza: ≥95% PET, ≤2% humedad
B44: Transporte/combustible mensual | C44: 15000 | D44: MXN/mes | E44: Supuesto operativo
B45: Agua y servicios mensual | C45: 4500 | D45: MXN/mes | E45: Supuesto operativo
B46: BLOQUE B — CAPEX CON CONSUMOS ENERGÉTICOS — PET
B47: Equipo | C47: Marca/Modelo | D47: Cant | E47: Precio unit MXN | F47: Total MXN | G47: kW nominal | H47: Factor util% | I47: Horas efect/día | J47: Días/mes | K47: kWh/mes | L47: kWh×1.10 | M47: Costo MXN/mes | N47: Nota
B48: Lavadora de PET industrial 500kg/h | C48: Amut/Genérica | D48: 1 | E48: 380000 | F48: =D48*E48 -> 380000 | G48: 22 | H48: 0.75 | I48: =H48*8 -> 6 | J48: =C10 -> 25 | K48: =G48*I48*J48*D48 -> 3300 | L48: =K48*C8 -> 3630 | M48: =L48*C5 -> 10890
B49: Trituradora/Molino PET 1t/h | C49: Vecoplan VNZ 63 | D49: 1 | E49: 520000 | F49: =D49*E49 -> 520000 | G49: 45 | H49: 0.75 | I49: =H49*8 -> 6 | J49: =C10 -> 25 | K49: =G49*I49*J49*D49 -> 6750 | L49: =K49*C8 -> 7425 | M49: =L49*C5 -> 22275
B50: Secador de flake centrífugo | C50: Genérico | D50: 1 | E50: 180000 | F50: =D50*E50 -> 180000 | G50: 15 | H50: 0.75 | I50: =H50*8 -> 6 | J50: =C10 -> 25 | K50: =G50*I50*J50*D50 -> 2250 | L50: =K50*C8 -> 2475 | M50: =L50*C5 -> 7425
B51: Banda transportadora 6m | C51: Nacional | D51: 2 | E51: 45000 | F51: =D51*E51 -> 90000 | G51: 1.5 | H51: 0.85 | I51: =H51*8 -> 6.8 | J51: =C10 -> 25 | K51: =G51*I51*J51*D51 -> 510 | L51: =K51*C8 -> 561 | M51: =L51*C5 -> 1683
B52: Extrusora pellet (escenario 80%) | C52: Genérica | D52: 1 | E52: 850000 | F52: =D52*E52 -> 850000 | G52: 75 | H52: 0.75 | I52: =H52*8 -> 6 | J52: =C10 -> 25 | K52: =G52*I52*J52*D52 -> 11250 | L52: =K52*C8 -> 12375 | M52: =L52*C5 -> 37125 | N52: Aplica solo en escenario 80%
B53: Báscula 1,000kg | C53: Torrey PLP1000 | D53: 1 | E53: 10000 | F53: =D53*E53 -> 10000 | G53: 0.1 | H53: 0.4 | I53: =H53*8 -> 3.2 | J53: =C10 -> 25 | K53: =G53*I53*J53*D53 -> 8 | L53: =K53*C8 -> 8.8 | M53: =L53*C5 -> 26.4
B54: Patín hidráulico | C54: Genérico | D54: 2 | E54: 8000 | F54: =D54*E54 -> 16000 | G54: 0 | K54: 0 | L54: =K54*C8 -> 0 | M54: =L54*C5 -> 0 | N54: Manual
B55: Herramienta menor | C55: Varios | D55: 1 | E55: 25000 | F55: =D55*E55 -> 25000 | G55: 0 | K55: 0 | L55: =K55*C8 -> 0 | M55: =L55*C5 -> 0
B56: TOTAL EQUIPAMIENTO | F56: =SUM(F48:F55) -> 2071000 | K56: =SUM(K48:K55) -> 24068 | L56: =SUM(L48:L55) -> 26474.8 | M56: =SUM(M48:M55) -> 79424.4
B58: BLOQUE C — CAPEX TOTAL — PET
B59: Concepto | C59: Monto MXN
B60: Equipamiento | C60: =F56 -> 2071000
B61: Adecuación de nave | C61: 200000
B62: Gastos preoperativos | C62: 55000
B63: Capital de trabajo (2 meses OPEX) | C63: =(C79-C68)*2 -> 1514994.8
B64: CAPEX TOTAL | C64: =SUM(C60:C63) -> 3840994.8
B66: BLOQUE D — OPEX MENSUAL — PET
B67: Concepto | C67: Esc 40% (base) | D67: Esc 30% | E67: Esc 80%
B68: CMV — Compra MP en centros de acopio (PET) | C68: =C34*C36*(1-C11)*C40*1000 -> 2694384 | D68: =C34*C35*(1-C11)*C40*1000 -> 2020788 | E68: =C34*C37*(1-C11)*C40*1000 -> 5388768
B69: Renta | C69: =C41*C12 -> 19500 | D69: =C69 -> 19500 | E69: =C69 -> 19500
B70: Energía eléctrica | C70: =M56 -> 79424.4 | D70: =C70*($C$35/$C$36) -> 59568.3 | E70: =C70*($C$37/$C$36) -> 158848.8 | F70: =C70*($C$37/$C$36) -> 158848.8
B71: Nómina con prestaciones | C71: =C42 -> 116775 | D71: =C71 -> 116775 | E71: =C71 -> 116775
B72: Transporte/combustible | C72: =$C$44 -> 15000 | D72: =C72*($C$35/$C$36) -> 11250 | E72: =C72*($C$37/$C$36) -> 30000 | F72: =C72*($C$37/$C$36) -> 30000
B73: Mantenimiento equipo (2.5% CAPEX/12) | C73: =C60*0.025/12 -> 4314.5833 | D73: =C73 -> 4314.5833 | E73: =C73 -> 4314.5833
B74: Insumos (agua proceso, empaques, químicos) | C74: =E94*0.03 -> 128448.63 | D74: =C74*($C$35/$C$36) -> 96336.475 | E74: =C74*($C$37/$C$36) -> 256897.27 | F74: =C74*($C$37/$C$36) -> 256897.27
B75: Agua y servicios | C75: =$C$45 -> 4500 | D75: =C75*($C$35/$C$36) -> 3375 | E75: =C75*($C$37/$C$36) -> 9000 | F75: =C75*($C$37/$C$36) -> 9000
B76: Seguros (0.5% CAPEX total / 12) | C76: =(C60+C61)*0.005/12 -> 946.25 | D76: =C76 -> 946.25 | E76: =C76 -> 946.25
B77: Flete a comprador (8% ingreso 40%) | C77: =E92*8/100 -> 380588.54
B78: Consumibles de línea (cuchillas, filtros, bandas, refacciones) | C78: 8000
B79: TOTAL OPEX MENSUAL | C79: =SUM(C68:C78) -> 3451881.4 | D79: =SUM(D68:D76) -> 2332853.6 | E79: =SUM(E68:E76) -> 5985049.9
B81: Nota analítica: La extrusora (escenario 80%) representa el componente de mayor CAPEX y consumo energético. Los escenarios 30-40% (flake) son más eficientes energéticamente.
B83: BLOQUE E — INGRESOS MENSUALES POR ESCENARIO — PET
B84: Concepto | C84: Unidad | D84: Esc 30% | E84: Esc 40% | F84: Esc 80%
B85: Volumen entrada t/mes, 100%= 90%= 1360,8 | C85: t/mes | D85: =C34*0.3 -> 408.24 | E85: =C34*0.4 -> 544.32 | F85: =C34*0.8 -> 1088.64
B86: Volumen procesado internamente t/mes | C86: t/mes | D86: =D85*C35 -> 122.472 | E86: =E85*C36 -> 217.728 | F86: =F85*C37 -> 870.912 | H86: Se asume que del 100% recolectado el 10% se perdera en trayecto y se quedara en los camiones, luego de ese 90%, asumimos, que los recicaldores podran comprarlo a 5,5 y procesarlo para despues comercializarlo , se crearon 3 escenarios de aprovechamiento, el 30%, 40% y 80%.
B87: Precio producto procesado MXN/kg | C87: MXN/kg | D87: =C39 -> 16 | E87: =C39 -> 16 | F87: =C39 -> 16
B88: Ingreso por material procesado | C88: MXN/mes | D88: =D86*1000*C38*D87 -> 1665619.2 | E88: =E86*1000*C38*E87 -> 2961100.8 | F88: =F86*1000*C38*F87 -> 11844403
B89: Volumen comercializado t/mes | C89: t/mes | D89: =D85*(1-C35) -> 285.768 | E89: =E85*(1-C36) -> 326.592 | F89: =F85*(1-C37) -> 217.728
B90: Precio comercialización MXN/kg | C90: MXN/kg | D90: =C40 -> 5.5 | E90: =C40 -> 5.5 | F90: =C40 -> 5.5
B91: Ingreso por comercialización | C91: MXN/mes | D91: =D89*1000*D90 -> 1571724 | E91: =E89*1000*E90 -> 1796256 | F91: =F89*1000*F90 -> 1197504
B92: INGRESO TOTAL MENSUAL | C92: MXN/mes | D92: =D88+D91 -> 3237343.2 | E92: =E88+E91 -> 4757356.8 | F92: =F88+F91 -> 13041907
B93: (–) Merma 10% | C93: MXN/mes | D93: =-D92*C11 -> -323734.32 | E93: =-E92*C11 -> -475735.68 | F93: =-F92*C11 -> -1304190.7
B94: INGRESO NETO MENSUAL | C94: MXN/mes | D94: =D92+D93 -> 2913608.9 | E94: =E92+E93 -> 4281621.1 | F94: =F92+F93 -> 11737716
B95: Precios de referencia marzo 2026. Sujetos a revisión trimestral con base en índices ANIPAC, CEMPRE México y cotizaciones directas de compradores ancla.
B97: BLOQUE F — ESTADO DE RESULTADOS P&L (Año 1 a Año 10) — PET
B98: P&L — Esc 30% (30% procesado)
B99: Concepto | C99: Año 1 | D99: Año 2 | E99: Año 3 | F99: Año 4 | G99: Año 5 | H99: Año 6 | I99: Año 7 | J99: Año 8 | K99: Año 9 | L99: Año 10
B100: Ingresos brutos | C100: =D92*12*C22 -> 19424059 | D100: =D92*12*C23 -> 29136089 | E100: =D92*12*C24 -> 38848118 | F100: =D92*12*C24 -> 38848118 | G100: =D92*12*C24 -> 38848118 | H100: =D92*12*C24 -> 38848118 | I100: =D92*12*C24 -> 38848118 | J100: =D92*12*C24 -> 38848118 | K100: =D92*12*C24 -> 38848118 | L100: =D92*12*C24 -> 38848118
B101: (–) Merma 10% | C101: =-C100*C11 -> -1942405.9 | D101: =-D100*C11 -> -2913608.9 | E101: =-E100*C11 -> -3884811.8 | F101: =-F100*C11 -> -3884811.8 | G101: =-G100*C11 -> -3884811.8 | H101: =-H100*C11 -> -3884811.8 | I101: =-I100*C11 -> -3884811.8 | J101: =-J100*C11 -> -3884811.8 | K101: =-K100*C11 -> -3884811.8 | L101: =-L100*C11 -> -3884811.8
B102: Ingresos netos | C102: =C100+C101 -> 17481653 | D102: =D100+D101 -> 26222480 | E102: =E100+E101 -> 34963307 | F102: =F100+F101 -> 34963307 | G102: =G100+G101 -> 34963307 | H102: =H100+H101 -> 34963307 | I102: =I100+I101 -> 34963307 | J102: =J100+J101 -> 34963307 | ... L102: =L100+L101 -> 34963307
B103: (–) OPEX total | C103: =-D79*12*C22 -> -13997122 | D103: =-D79*12*C23 -> -20995682 | E103: =-D79*12*C24 -> -27994243 | F103: =-$D$79*12*$C$24 -> -27994243 | G103: =-$D$79*12*$C$24 -> -27994243 | H103: =-$D$79*12*$C$24 -> -27994243 | I103: =-$D$79*12*$C$24 -> -27994243 | J103: =-$D$79*12*$C$24 -> -27994243 | K103: =-$D$79*12*$C$24 -> -27994243 | L103: =-C79*12*C24 -> -41422577
B104: EBITDA | C104: =C102+C103 -> 3484531.6 | D104: =D102+D103 -> 5226797.4 | E104: =E102+E103 -> 6969063.3 | F104: =F102+F103 -> 6969063.3 | G104: =G102+G103 -> 6969063.3 | H104: =H102+H103 -> 6969063.3 | I104: =I102+I103 -> 6969063.3 | J104: =J102+J103 -> 6969063.3 | ... L104: =L102+L103 -> -6459270.4
B105: Margen EBITDA % | C105: =IF(C102=0,0,C104/C102) -> 0.19932506 | D105: =IF(D102=0,0,D104/D102) -> 0.19932506 | E105: =IF(E102=0,0,E104/E102) -> 0.19932506 | F105: =IF(F102=0,0,F104/F102) -> 0.19932506 | G105: =IF(G102=0,0,G104/G102) -> 0.19932506 | H105: =IF(H102=0,0,H104/H102) -> 0.19932506 | I105: =IF(I102=0,0,I104/I102) -> 0.19932506 | J105: =IF(J102=0,0,J104/J102) -> 0.19932506 | ... L105: =IF(L102=0,0,L104/L102) -> -0.18474426
B106: (–) Depreciación y amortización | C106: =-(C60/C18+C61/20) -> -217100 | D106: =-(C60/C18+C61/20) -> -217100 | E106: =-(C60/C18+C61/20) -> -217100 | F106: =-(C60/C18+C61/20) -> -217100 | G106: =-(C60/C18+C61/20) -> -217100 | H106: =-(C60/C18+C61/20) -> -217100 | I106: =-(C60/C18+C61/20) -> -217100 | J106: =-(C60/C18+C61/20) -> -217100 | K106: =-(C60/C18+C61/20) -> -217100 | L106: =-(C60/C18+C61/20) -> -217100
...

Sheet Papel-Carton
B2: BLOQUE A — SUPUESTOS PARAMETRIZADOS — PAPEL-CARTON
B3: Parámetro | C3: Valor | D3: Unidad | E3: Fuente / Nota
B4: Tipo de cambio USD/MXN | C4: 17.1 | D4: MXN/USD
B5: Tarifa eléctrica industrial SLP | C5: 3 | D5: MXN/kWh | E5: Ref CFE tarifa GDMTH SLP
B6: Precio gas LP industrial | C6: 18.5 | D6: MXN/kg | E6: Supuesto razonado
B7: Precio diésel | C7: 26 | D7: MXN/litro | E7: Supuesto razonado
B8: Factor contingencia energética | C8: 1.1 | D8: x
B9: Días operativos/año | C9: 300 | D9: días
B10: Días operativos/mes | C10: 25 | D10: días
B11: Merma estimada | C11: 0.1 | D11: %
B12: Renta zona industrial | C12: 65 | D12: MXN/m²/mes
B13: Factor prestaciones sociales | C13: 1.35 | D13: x
B14: WACC | C14: 0.2 | D14: %
B15: ISR | C15: 0.3 | D15: %
B16: PTU | C16: 0.1 | D16: %
B17: Reserva legal | C17: 0.05 | D17: %
B18: Vida útil maquinaria industrial | C18: 10 | D18: años
B19: Vida útil transporte | C19: 4 | D19: años
... B27: DPO (días cuentas por pagar) | C27: 15 | D27: días
B28: Múltiplo valor terminal EBITDA | C28: 5 | D28: x | E28: Rango 4-6x
B29: Estructura D/E (% deuda) | C29: 0.6 | D29: % | E29: 60/40
B30: Tasa interés deuda | C30: 0.135 | D30: % anual
B31: Plazo deuda | C31: 6 | D31: años
B33: Parámetros específicos — Papel-Carton
B34: Volumen entrada t/mes | C34: 3628.8 | D34: t/mes | E34: Supuesto razonado
B35: Escenario % procesado 30% | C35: 0.3 | D35: % | E35: =$C$34*C35 -> 1088.64 | G35: Se asume que del 100% recolectado el 10% se perdera en trayecto y se quedara en los camiones, luego de ese 90%, asumimos, que los recicaldores podran comprarlo a 2,5 y procesarlo para despues comercializarlo , se crearon 3 escenarios de aprovechamiento, el 30%, 40% y 80%.
B36: Escenario % procesado 40% | C36: 0.4 | D36: % | E36: =$C$34*C36 -> 1451.52
B37: Escenario % procesado 80% | C37: 0.8 | D37: % | E37: =$C$34*C37 -> 2903.04
B38: Rendimiento proceso kg/kg entrada | C38: 0.9 | D38: kg/kg
B39: Precio Papel-Carton procesado | C39: 4.5 | D39: MXN/kg | E39: Valor agregado
B40: Precio compra MP centros de acopio (Papel-Cartón) | C40: 2.5 | D40: MXN/kg
B41: Nave industrial m² | C41: 600 | D41: m²
B42: Nómina mensual (8 operarios + 2 supervisores + 1 chofer) | C42: 175500 | D42: MXN/mes | E42: (8*10000+2*17500+1*13500)*1.35
B43: Compradores ancla | C43: MRS Logística SLP, Grupo Altsa, Bio Pappel Monterrey | E43: Condiciones: humedad <12%, sin cartón bituminoso
B44: Transporte/combustible mensual | C44: 25000 | D44: MXN/mes | E44: Supuesto operativo (volumen mayor Papel-Cartón)
B45: Agua y servicios mensual | C45: 4500 | D45: MXN/mes | E45: Supuesto operativo
B46: BLOQUE B — CAPEX CON CONSUMOS ENERGÉTICOS — PAPEL-CARTON
B47: Equipo | C47: Marca/Modelo | D47: Cant | E47: Precio unit MXN | F47: Total MXN | G47: kW nominal | H47: Factor util% | I47: Horas efect/día | J47: Días/mes | K47: kWh/mes | L47: kWh×1.10 | M47: Costo MXN/mes | N47: Nota
B48: Prensa embaladora horizontal 5t/h | C48: TEVA/Imabe | D48: 1 | E48: 680000 | F48: =D48*E48 -> 680000 | G48: 22 | H48: 0.75 | I48: =H48*8 -> 6 | J48: =C10 -> 25 | K48: =G48*I48*J48*D48 -> 3300 | L48: =K48*C8 -> 3630 | M48: =L48*C5 -> 10890
B49: Guillotina/Trituradora cartón | C49: Nacional | D49: 1 | E49: 280000 | F49: =D49*E49 -> 280000 | G49: 15 | H49: 0.7 | I49: =H49*8 -> 5.6 | J49: =C10 -> 25 | K49: =G49*I49*J49*D49 -> 2100 | L49: =K49*C8 -> 2310 | M49: =L49*C5 -> 6930
B50: Banda transportadora 10m | C50: Nacional | D50: 2 | E50: 55000 | F50: =D50*E50 -> 110000 | G50: 2.2 | H50: 0.85 | I50: =H50*8 -> 6.8 | J50: =C10 -> 25 | K50: =G50*I50*J50*D50 -> 748 | L50: =K50*C8 -> 822.8 | M50: =L50*C5 -> 2468.4
B51: Báscula 3,000kg | C51: Torrey PLP3000 | D51: 1 | E51: 19000 | F51: =D51*E51 -> 19000 | G51: 0.1 | H51: 0.4 | I51: =H51*8 -> 3.2 | J51: =C10 -> 25 | K51: =G51*I51*J51*D51 -> 8 | L51: =K51*C8 -> 8.8 | M51: =L51*C5 -> 26.4
B52: Montacargas gas LP | C52: Toyota 8FGU25 | D52: 1 | E52: 425000 | F52: =D52*E52 -> 425000 | G52: 0 | H52: 0.6 | K52: 0 | L52: =K52*C8 -> 0 | M52: =L52*C5 -> 0 | N52: Gas LP: 2.5 kg/hora
B53: Herramienta menor | C53: Varios | D53: 1 | E53: 30000 | F53: =D53*E53 -> 30000 | G53: 0 | K53: 0 | L53: =K53*C8 -> 0 | M53: =L53*C5 -> 0
B54: COSTO GAS LP MENSUAL (equipos) | M54: =2.5*I52*J52*C6 -> 0
B55: TOTAL EQUIPAMIENTO | F55: =SUM(F48:F53) -> 1544000 | K55: =SUM(K48:K53) -> 6156 | L55: =SUM(L48:L53) -> 6771.6 | M55: =SUM(M48:M53)+M54 -> 20314.8
B57: BLOQUE C — CAPEX TOTAL — PAPEL-CARTON
B58: Concepto | C58: Monto MXN
B59: Equipamiento | C59: =F55 -> 1544000
B60: Adecuación de nave | C60: 280000
B61: Gastos preoperativos | C61: 55000
B62: Capital de trabajo (2 meses OPEX) | C62: =(C79-C67)*2 -> 1517733.8
B63: CAPEX TOTAL | C63: =SUM(C59:C62) -> 3396733.8
B65: BLOQUE D — OPEX MENSUAL — PAPEL-CARTON
B66: Concepto | C66: MXN/mes
B67: CMV — Compra MP en centros de acopio (Papel-Cartón) | C67: =C34*C36*(1-C11)*C40*1000 -> 3265920
B68: Renta | C68: =C41*C12 -> 39000
B69: Energía eléctrica | C69: =M55 -> 20314.8
B70: Combustible gas LP (equipos) | C70: =M54 -> 0
B71: Nómina con prestaciones | C71: =C42 -> 175500
B72: Transporte/combustible | C72: =$C$44 -> 25000
B73: Mantenimiento equipo (2.5% CAPEX/12) | C73: =C59*0.025/12 -> 3216.6667
B74: Insumos (agua proceso, empaques, químicos) | C74: =E93*0.03 -> 122276.04
B75: Agua y servicios | C75: =$C$45 -> 4500
B76: Seguros (0.5% CAPEX total / 12) | C76: =(C59+C60)*0.005/12 -> 760
B77: Flete a comprador (8% ingreso 40%) | C77: =E91*8/100 -> 362299.39
B78: Consumibles de línea (cuchillas, filtros, bandas, refacciones) | C78: 6000
B79: TOTAL OPEX MENSUAL | C79: =SUM(C67:C78) -> 4024786.9
B80: Nota analítica: RIESGO PRINCIPAL: humedad. El costo de nave seca (techo reforzado, ventilación baja humedad) es el componente de mayor sensibilidad del CAPEX. Nave impermeable obligatoria.
B82: BLOQUE E — INGRESOS MENSUALES POR ESCENARIO — PAPEL-CARTON
B83: Concepto | C83: Unidad | D83: Esc 30% | E83: Esc 40% | F83: Esc 80%
B84: Volumen entrada t/mes | C84: t/mes | D84: =C34*C35 -> 1088.64 | E84: =C34*C36 -> 1451.52 | F84: =C34*C37 -> 2903.04
B85: Volumen procesado internamente t/mes | C85: t/mes | D85: =D84*C35 -> 326.592 | E85: =E84*C36 -> 580.608 | F85: =F84*C37 -> 2322.432
B86: Precio producto procesado MXN/kg | C86: MXN/kg | D86: =C39 -> 4.5 | E86: =C39 -> 4.5 | F86: =C39 -> 4.5
B87: Ingreso por material procesado | C87: MXN/mes | D87: =D85*1000*C38*D86 -> 1322697.6 | E87: =E85*1000*C38*E86 -> 2351462.4 | F87: =F85*1000*C38*F86 -> 9405849.6
B88: Volumen comercializado t/mes | C88: t/mes | D88: =D84*(1-C35) -> 762.048 | E88: =E84*(1-C36) -> 870.912 | F88: =F84*(1-C37) -> 580.608
B89: Precio comercialización MXN/kg | C89: MXN/kg | D89: =C40 -> 2.5 | E89: =C40 -> 2.5 | F89: =C40 -> 2.5
B90: Ingreso por comercialización | C90: MXN/mes | D90: =D88*1000*D89 -> 1905120 | E90: =E88*1000*E89 -> 2177280 | F90: =F88*1000*F89 -> 1451520
B91: INGRESO TOTAL MENSUAL | C91: MXN/mes | D91: =D87+D90 -> 3227817.6 | E91: =E87+E90 -> 4528742.4 | F91: =F87+F90 -> 10857370
B92: (–) Merma 10% | C92: MXN/mes | D92: =-D91*C11 -> -322781.76 | E92: =-E91*C11 -> -452874.24 | F92: =-F91*C11 -> -1085737
B93: INGRESO NETO MENSUAL | C93: MXN/mes | D93: =D91+D92 -> 2905035.8 | E93: =E91+E92 -> 4075868.2 | F93: =F91+F92 -> 9771632.6
B94: Precios de referencia marzo 2026. Sujetos a revisión trimestral con base en índices ANIPAC, CEMPRE México y cotizaciones directas de compradores ancla.
B96: BLOQUE F — ESTADO DE RESULTADOS P&L (Año 1 a Año 10) — PAPEL-CARTON
B97: P&L — Esc 30% (30% procesado)
B98: Concepto | C98: Año 1 | D98: Año 2 | E98: Año 3 | F98: Año 4 | G98: Año 5 | H98: Año 6 | I98: Año 7 | J98: Año 8 | K98: Año 9 | L98: Año 10
B99: Ingresos brutos | C99: =D91*12*C22 -> 19366906 | D99: =D91*12*C23 -> 29050358 | E99: =D91*12*C24 -> 38733811 | F99: =D91*12*C24 -> 38733811 | G99: =D91*12*C24 -> 38733811 | H99: =D91*12*C24 -> 38733811 | I99: =D91*12*C24 -> 38733811 | J99: =D91*12*C24 -> 38733811 | K99: =D91*12*C24 -> 38733811 | L99: =D91*12*C24 -> 38733811
B100: (–) Merma 10% | C100: =-C99*C11 -> -1936690.6 | D100: =-D99*C11 -> -2905035.8 | E100: =-E99*C11 -> -3873381.1 | F100: =-F99*C11 -> -3873381.1 | G100: =-G99*C11 -> -3873381.1 | H100: =-H99*C11 -> -3873381.1 | I100: =-I99*C11 -> -3873381.1 | J100: =-J99*C11 -> -3873381.1 | K100: =-K99*C11 -> -3873381.1 | L100: =-L99*C11 -> -3873381.1
B101: Ingresos netos | C101: =C99+C100 -> 17430215 | D101: =D99+D100 -> 26145323 | E101: =E99+E100 -> 34860430 | F101: =F99+F100 -> 34860430 | G101: =G99+G100 -> 34860430 | H101: =H99+H100 -> 34860430 | I101: =I99+I100 -> 34860430 | J101: =J99+J100 -> 34860430 | ... L101: =L99+L100 -> 34860430
B102: (–) OPEX total | C102: =-C79*12*C22 -> -24148721 | D102: =-C79*12*C23 -> -36223082 | E102: =-C79*12*C24 -> -48297443 | F102: =-C79*12*C24 -> -48297443 | G102: =-C79*12*C24 -> -48297443 | H102: =-C79*12*C24 -> -48297443 | I102: =-C79*12*C24 -> -48297443 | J102: =-C79*12*C24 -> -48297443 | K102: =-C79*12*C24 -> -48297443 | L102: =-C79*12*C24 -> -48297443
B104: EBITDA | C104: =C101+C102 -> -6718506.4 | D104: =D101+D102 -> -10077760 | E104: =E101+E102 -> -13437013 | F104: =F101+F102 -> -13437013 | G104: =G101+G102 -> -13437013 | H104: =H101+H102 -> -13437013 | I104: =I101+I102 -> -13437013 | J104: =J101+J102 -> -13437013 | ... L104: =L101+L102 -> -13437013
B105: Margen EBITDA % | C105: =IF(C101=0,0,C104/C101) -> -0.38545172 | D105: =IF(D101=0,0,D104/D101) -> -0.38545172 | E105: =IF(E101=0,0,E104/E101) -> -0.38545172 | F105: =IF(F101=0,0,F104/F101) -> -0.38545172 | G105: =IF(G101=0,0,G104/G101) -> -0.38545172 | H105: =IF(H101=0,0,H104/H101) -> -0.38545172 | I105: =IF(I101=0,0,I104/I101) -> -0.38545172 | J105: =IF(J101=0,0,J104/J101) -> -0.38545172 | ... L105: =IF(L101=0,0,L104/L101) -> -0.38545172
B106: (–) Depreciación y amortización | C106: =-(C59/C18+C60/20) -> -168400 | D106: =-(C59/C18+C60/20) -> -168400 | E106: =-(C59/C18+C60/20) -> -168400 | F106: =-(C59/C18+C60/20) -> -168400 | G106: =-(C59/C18+C60/20) -> -168400 | H106: =-(C59/C18+C60/20) -> -168400 | I106: =-(C59/C18+C60/20) -> -168400 | J106: =-(C59/C18+C60/20) -> -168400 | K106: =-(C59/C18+C60/20) -> -168400 | L106: =-(C59/C18+C60/20) -> -168400
B108: EBIT | C108: =C104+C106 -> -6886906.4 | D108: =D104+D106 -> -10246160 | E108: =E104+E106 -> -13605413 | F108: =F104+F106 -> -13605413 | G108: =G104+G106 -> -13605413 | H108: =H104+H106 -> -13605413 | I108: =I104+I106 -> -13605413 | J108: =J104+J106 -> -13605413 | ... L108: =L104+L106 -> -13605413
B109: (–) Intereses | C109: =-D175 -> -275135.44 | D109: =-E175 -> -229279.53 | E109: =-F175 -> -183423.63 | F109: =-G175 -> -137567.72 | G109: =-H175 -> -91711.813 | H109: =-I175 -> -45855.906 | I109: =-J175 -> 0 | J109: =-K175 -> 0 | ... L109: =-M175 -> 0
B110: EBT | C110: =C108+C109 -> -7162041.8 | D110: =D108+D109 -> -10475439 | E110: =E108+E109 -> -13788836 | F110: =F108+F109 -> -13742980 | G110: =G108+G109 -> -13697125 | H110: =H108+H109 -> -13651269 | I110: =I108+I109 -> -13605413 | J110: =J108+J109 -> -13605413 | ... L110: =L108+L109 -> -13605413
B111: (–) ISR 30% | C111: =-MAX(0,C110)*C15 -> 0 | D111: =-MAX(0,D110)*C15 -> 0 | E111: =-MAX(0,E110)*C15 -> 0 | F111: =-MAX(0,F110)*C15 -> 0 | G111: =-MAX(0,G110)*C15 -> 0 | H111: =-MAX(0,H110)*C15 -> 0 | I111: =-MAX(0,I110)*C15 -> 0 | J111: =-MAX(0,J110)*C15 -> 0 | K111: =-MAX(0,K110)*C15 -> 0 | L111: =-MAX(0,L110)*C15 -> 0
B112: (–) PTU 10% | C112: =-MAX(0,C110)*C16 -> 0 | D112: =-MAX(0,D110)*C16 -> 0 | E112: =-MAX(0,E110)*C16 -> 0 | F112: =-MAX(0,F110)*C16 -> 0 | G112: =-MAX(0,G110)*C16 -> 0 | H112: =-MAX(0,H110)*C16 -> 0 | I112: =-MAX(0,I110)*C16 -> 0 | J112: =-MAX(0,J110)*C16 -> 0 | K112: =-MAX(0,K110)*C16 -> 0 | L112: =-MAX(0,L110)*C16 -> 0
B114: Utilidad neta | C114: =C110+C111+C112 -> -7162041.8 | D114: =D110+D111+D112 -> -10475439 | E114: =E110+E111+E112 -> -13788836 | F114: =F110+F111+F112 -> -13742980 | G114: =G110+G111+G112 -> -13697125 | H114: =H110+H111+H112 -> -13651269 | I114: =I110+I111+I112 -> -13605413 | J114: =J110+J111+J112 -> -13605413 | ... L114: =L110+L111+L112 -> -13605413
B115: (–) Reserva legal 5% | C115: =-MAX(0,C114)*C17 -> 0 | D115: =-MAX(0,D114)*C17 -> 0 | E115: =-MAX(0,E114)*C17 -> 0 | F115: =-MAX(0,F114)*C17 -> 0 | G115: =-MAX(0,G114)*C17 -> 0 | H115: =-MAX(0,H114)*C17 -> 0 | I115: =-MAX(0,I114)*C17 -> 0 | J115: =-MAX(0,J114)*C17 -> 0 | K115: =-MAX(0,K114)*C17 -> 0 | L115: =-MAX(0,L114)*C17 -> 0
B116: Utilidad distribuible | C116: =C114+C115 -> -7162041.8 | D116: =D114+D115 -> -10475439 | E116: =E114+E115 -> -13788836 | F116: =F114+F115 -> -13742980 | G116: =G114+G115 -> -13697125 | H116: =H114+H115 -> -13651269 | I116: =I114+I115 -> -13605413 | J116: =J114+J115 -> -13605413 | ... L116: =L114+L115 -> -13605413
...

Sheet Aluminio
B2: BLOQUE A — SUPUESTOS PARAMETRIZADOS — ALUMINIO
B3: Parámetro | C3: Valor | D3: Unidad | E3: Fuente / Nota
B4: Tipo de cambio USD/MXN | C4: 17.1 | D4: MXN/USD
B5: Tarifa eléctrica industrial SLP | C5: 3 | D5: MXN/kWh | E5: Ref CFE tarifa GDMTH SLP
B6: Precio gas LP industrial | C6: 18.5 | D6: MXN/kg | E6: Supuesto razonado
B7: Precio diésel | C7: 26 | D7: MXN/litro | E7: Supuesto razonado
B8: Factor contingencia energética | C8: 1.1 | D8: x
B9: Días operativos/año | C9: 300 | D9: días
B10: Días operativos/mes | C10: 25 | D10: días
B11: Merma estimada | C11: 0.1 | D11: %
B12: Renta zona industrial | C12: 65 | D12: MXN/m²/mes
B13: Factor prestaciones sociales | C13: 1.35 | D13: x
B14: WACC | C14: 0.2 | D14: %
B15: ISR | C15: 0.3 | D15: %
B16: PTU | C16: 0.1 | D16: %
B17: Reserva legal | C17: 0.05 | D17: %
B18: Vida útil maquinaria industrial | C18: 10 | D18: años
B19: Vida útil transporte | C19: 4 | D19: años
... B27: DPO (días cuentas por pagar) | C27: 15 | D27: días
B28: Múltiplo valor terminal EBITDA | C28: 5 | D28: x | E28: Rango 4-6x
B29: Estructura D/E (% deuda) | C29: 0.6 | D29: % | E29: 60/40
B30: Tasa interés deuda | C30: 0.135 | D30: % anual
B31: Plazo deuda | C31: 6 | D31: años
B33: Parámetros específicos — Aluminio
B34: Volumen entrada t/mes | C34: 571.536 | D34: t/mes | E34: Supuesto razonado
B35: Escenario % procesado 30% | C35: 0.3 | D35: % | E35: 30%=municipio
B36: Escenario % procesado 40% | C36: 0.4 | D36: % | E36: 40%=concesionario
B37: Escenario % procesado 80% | C37: 0.8 | D37: % | E37: 80%=fondos de impacto
B38: Rendimiento proceso kg/kg entrada | C38: 0.85 | D38: kg/kg
B39: Precio Aluminio procesado | C39: 42 | D39: MXN/kg | E39: Valor agregado
B40: Precio compra MP centros de acopio (Aluminio) | C40: 15.1 | D40: MXN/kg
B41: Nave industrial m² | C41: 250 | D41: m²
B42: Nómina mensual (5 operarios + 1 supervisor + 1 fundidor especialista) | C42: 107325 | D42: MXN/mes | E42: (5*10000+1*17500+1*22000)*1.35
B43: Compradores ancla | C43: RRECIMETSA, ARZYZ, industria metalmecánica SLP | E43: Pureza ≥98% Al, sin pintura ni recubrimientos
B44: Transporte/combustible mensual | C44: 12000 | D44: MXN/mes | E44: Supuesto operativo
B45: Agua y servicios mensual | C45: 3500 | D45: MXN/mes | E45: Supuesto operativo
B46: BLOQUE B — CAPEX CON CONSUMOS ENERGÉTICOS — ALUMINIO
B47: Equipo | C47: Marca/Modelo | D47: Cant | E47: Precio unit MXN | F47: Total MXN | G47: kW nominal | H47: Factor util% | I47: Horas efect/día | J47: Días/mes | K47: kWh/mes | L47: kWh×1.10 | M47: Costo MXN/mes | N47: Nota
B48: Horno fundición aluminio 300kg/carga | C48: Nacional/Importado | D48: 1 | E48: 1200000 | F48: =D48*E48 -> 1200000 | G48: 90 | H48: 0.65 | I48: =H48*8 -> 5.2 | J48: =C10 -> 25 | K48: =G48*I48*J48*D48 -> 11700 | L48: =K48*C8 -> 12870 | M48: =L48*C5 -> 38610 | N48: Usa gas LP: 18 kg/hora
B49: Prensa compactadora aluminio | C49: Genérica | D49: 1 | E49: 280000 | F49: =D49*E49 -> 280000 | G49: 22 | H49: 0.7 | I49: =H49*8 -> 5.6 | J49: =C10 -> 25 | K49: =G49*I49*J49*D49 -> 3080 | L49: =K49*C8 -> 3388 | M49: =L49*C5 -> 10164
B50: Banda transportadora 6m | C50: Nacional | D50: 1 | E50: 45000 | F50: =D50*E50 -> 45000 | G50: 1.5 | H50: 0.8 | I50: =H50*8 -> 6.4 | J50: =C10 -> 25 | K50: =G50*I50*J50*D50 -> 240 | L50: =K50*C8 -> 264 | M50: =L50*C5 -> 792
B51: Lingoteras + equipo colado | C51: Nacional | D51: 1 | E51: 120000 | F51: =D51*E51 -> 120000 | G51: 0 | K51: 0 | L51: =K51*C8 -> 0 | M51: =L51*C5 -> 0
B52: Báscula 500kg | C52: Rhino | D52: 1 | E52: 3800 | F52: =D52*E52 -> 3800 | G52: 0.1 | H52: 0.4 | I52: =H52*8 -> 3.2 | J52: =C10 -> 25 | K52: =G52*I52*J52*D52 -> 8 | L52: =K52*C8 -> 8.8 | M52: =L52*C5 -> 26.4
B53: EPI protección individual | C53: Varios | D53: 1 | E53: 35000 | F53: =D53*E53 -> 35000 | G53: 0 | K53: 0 | L53: =K53*C8 -> 0 | M53: =L53*C5 -> 0 | N53: Costo único
B54: Herramienta menor | C54: Varios | D54: 1 | E54: 25000 | F54: =D54*E54 -> 25000 | G54: 0 | K54: 0 | L54: =K54*C8 -> 0 | M54: =L54*C5 -> 0
B55: COSTO GAS LP MENSUAL (equipos) | M55: =18*I48*J48*C6 -> 43290
B56: TOTAL EQUIPAMIENTO | F56: =SUM(F48:F54) -> 1708800 | K56: =SUM(K48:K54) -> 15028 | L56: =SUM(L48:L54) -> 16530.8 | M56: =SUM(M48:M54)+M55 -> 92882.4
B58: BLOQUE C — CAPEX TOTAL — ALUMINIO
B59: Concepto | C59: Monto MXN
B60: Equipamiento | C60: =F56 -> 1708800
B61: Adecuación de nave | C61: 350000
B62: Gastos preoperativos | C62: 95000
B63: Capital de trabajo (2 meses OPEX) | C63: =(C80-C68)*2 -> 1711204.5
B64: CAPEX TOTAL | C64: =SUM(C60:C63) -> 3865004.5
B66: BLOQUE D — OPEX MENSUAL — ALUMINIO
B67: Concepto | C67: MXN/mes
B68: CMV — Compra MP en centros de acopio (Aluminio) | C68: =C34*C36*(1-C11)*C40*1000 -> 3106869.7
B69: Renta | C69: =C41*C12 -> 16250
B70: Energía eléctrica | C70: =M56 -> 92882.4
B71: Combustible gas LP (equipos) | C71: =M55 -> 43290
B72: Nómina con prestaciones | C72: =C42 -> 107325
B73: Transporte/combustible | C73: =$C$44 -> 12000
B74: Mantenimiento equipo (2.5% CAPEX/12) | C74: =C60*0.025/12 -> 3560
B75: Insumos (agua proceso, empaques, químicos) | C75: =E94*0.03 -> 144068.22
B76: Agua y servicios | C76: =$C$45 -> 3500
B77: Seguros (0.5% CAPEX total / 12) | C77: =(C60+C61)*0.005/12 -> 857.83333
B78: Flete a comprador (8% ingreso 40%) | C78: =E92*8/100 -> 426868.81
B79: Consumibles de línea (cuchillas, filtros, bandas, refacciones) | C79: 5000
B80: TOTAL OPEX MENSUAL | C80: =SUM(C68:C79) -> 3962472
B81: Nota analítica: RIESGO PRINCIPAL: El horno es el CAPEX más alto y el consumo energético más intensivo. En el escenario 30% puede ser más rentable que el 80% si el precio del gas LP supera $25/kg. La fundición requiere licencia ambiental especial.
B83: BLOQUE E — INGRESOS MENSUALES POR ESCENARIO — ALUMINIO
B84: Concepto | C84: Unidad | D84: Esc 30% | E84: Esc 40% | F84: Esc 80%
B85: Volumen entrada t/mes | C85: t/mes | D85: =C34*C35 -> 171.4608 | E85: =C34*C36 -> 228.6144 | F85: =C34*C37 -> 457.2288
B86: Volumen procesado internamente t/mes | C86: t/mes | D86: =D85*C35 -> 51.43824 | E86: =E85*C36 -> 91.44576 | F86: =F85*C37 -> 365.78304 | H86: Se asume que del 100% recolectado el 10% se perdera en trayecto y se quedara en los camiones, luego de ese 90%, asumimos, que los recicaldores podran comprarlo a 15,10 y procesarlo para despues comercializarlo , se crearon 3 escenarios de aprovechamiento, el 30%, 40% y 80%.
B87: Precio producto procesado MXN/kg | C87: MXN/kg | D87: =C39 -> 42 | E87: =C39 -> 42 | F87: =C39 -> 42
B88: Ingreso por material procesado | C88: MXN/mes | D88: =D86*1000*C38*D87 -> 1836345.2 | E88: =E86*1000*C38*E87 -> 3264613.6 | F88: =F86*1000*C38*F87 -> 13058455
B89: Volumen comercializado t/mes | C89: t/mes | D89: =D85*(1-C35) -> 120.02256 | E89: =E85*(1-C36) -> 137.16864 | F89: =F85*(1-C37) -> 91.44576
B90: Precio comercialización MXN/kg | C90: MXN/kg | D90: =C40 -> 15.1 | E90: =C40 -> 15.1 | F90: =C40 -> 15.1
B91: Ingreso por comercialización | C91: MXN/mes | D91: =D89*1000*D90 -> 1812340.7 | E91: =E89*1000*E90 -> 2071246.5 | F91: =F89*1000*F90 -> 1380831
B92: INGRESO TOTAL MENSUAL | C92: MXN/mes | D92: =D88+D91 -> 3648685.8 | E92: =E88+E91 -> 5335860.1 | F92: =F88+F91 -> 14439286
B93: (–) Merma 10% | C93: MXN/mes | D93: =-D92*C11 -> -364868.58 | E93: =-E92*C11 -> -533586.01 | F93: =-F92*C11 -> -1443928.6
B94: INGRESO NETO MENSUAL | C94: MXN/mes | D94: =D92+D93 -> 3283817.2 | E94: =E92+E93 -> 4802274.1 | F94: =F92+F93 -> 12995357
B95: Precios de referencia marzo 2026. Sujetos a revisión trimestral con base en índices ANIPAC, CEMPRE México y cotizaciones directas de compradores ancla.
B97: BLOQUE F — ESTADO DE RESULTADOS P&L (Año 1 a Año 10) — ALUMINIO
B98: P&L — Esc 30% (30% procesado)
B99: Concepto | C99: Año 1 | D99: Año 2 | E99: Año 3 | F99: Año 4 | G99: Año 5 | H99: Año 6 | I99: Año 7 | J99: Año 8 | K99: Año 9 | L99: Año 10
B100: Ingresos brutos | C100: =D92*12*C22 -> 21892115 | D100: =D92*12*C23 -> 32838172 | E100: =D92*12*C24 -> 43784230 | F100: =D92*12*C24 -> 43784230 | G100: =D92*12*C24 -> 43784230 | H100: =D92*12*C24 -> 43784230 | I100: =D92*12*C24 -> 43784230 | J100: =D92*12*C24 -> 43784230 | K100: =D92*12*C24 -> 43784230 | L100: =D92*12*C24 -> 43784230
B101: (–) Merma 10% | C101: =-C100*C11 -> -2189211.5 | D101: =-D100*C11 -> -3283817.2 | E101: =-E100*C11 -> -4378423 | F101: =-F100*C11 -> -4378423 | G101: =-G100*C11 -> -4378423 | H101: =-H100*C11 -> -4378423 | I101: =-I100*C11 -> -4378423 | J101: =-J100*C11 -> -4378423 | K101: =-K100*C11 -> -4378423 | L101: =-L100*C11 -> -4378423
B102: Ingresos netos | C102: =C100+C101 -> 19702903 | D102: =D100+D101 -> 29554355 | E102: =E100+E101 -> 39405807 | F102: =F100+F101 -> 39405807 | G102: =G100+G101 -> 39405807 | H102: =H100+H101 -> 39405807 | I102: =I100+I101 -> 39405807 | J102: =J100+J101 -> 39405807 | ... L102: =L100+L101 -> 39405807
B103: (–) OPEX total | C103: =-C80*12*C22 -> -23774832 | D103: =-C80*12*C23 -> -35662248 | E103: =-C80*12*C24 -> -47549664 | F103: =-C80*12*C24 -> -47549664 | G103: =-C80*12*C24 -> -47549664 | H103: =-C80*12*C24 -> -47549664 | I103: =-C80*12*C24 -> -47549664 | J103: =-C80*12*C24 -> -47549664 | K103: =-C80*12*C24 -> -47549664 | L103: =-C80*12*C24 -> -47549664
B104: EBITDA | C104: =C102+C103 -> -4071928.3 | D104: =D102+D103 -> -6107892.5 | E104: =E102+E103 -> -8143856.6 | F104: =F102+F103 -> -8143856.6 | G104: =G102+G103 -> -8143856.6 | H104: =H102+H103 -> -8143856.6 | I104: =I102+I103 -> -8143856.6 | J104: =J102+J103 -> -8143856.6 | ... L104: =L102+L103 -> -8143856.6
B105: Margen EBITDA % | C105: =IF(C102=0,0,C104/C102) -> -0.20666641 | D105: =IF(D102=0,0,D104/D102) -> -0.20666641 | E105: =IF(E102=0,0,E104/E102) -> -0.20666641 | F105: =IF(F102=0,0,F104/F102) -> -0.20666641 | G105: =IF(G102=0,0,G104/G102) -> -0.20666641 | H105: =IF(H102=0,0,H104/H102) -> -0.20666641 | I105: =IF(I102=0,0,I104/I102) -> -0.20666641 | J105: =IF(J102=0,0,J104/J102) -> -0.20666641 | ... L105: =IF(L102=0,0,L104/L102) -> -0.20666641
B106: (–) Depreciación y amortización | C106: =-(C60/C18+C61/20) -> -188380 | D106: =-(C60/C18+C61/20) -> -188380 | E106: =-(C60/C18+C61/20) -> -188380 | F106: =-(C60/C18+C61/20) -> -188380 | G106: =-(C60/C18+C61/20) -> -188380 | H106: =-(C60/C18+C61/20) -> -188380 | I106: =-(C60/C18+C61/20) -> -188380 | J106: =-(C60/C18+C61/20) -> -188380 | K106: =-(C60/C18+C61/20) -> -188380 | L106: =-(C60/C18+C61/20) -> -188380
B107: EBIT | C107: =C104+C106 -> -4260308.3 | D107: =D104+D106 -> -6296272.5 | E107: =E104+E106 -> -8332236.6 | F107: =F104+F106 -> -8332236.6 | G107: =G104+G106 -> -8332236.6 | H107: =H104+H106 -> -8332236.6 | I107: =I104+I106 -> -8332236.6 | J107: =J104+J106 -> -8332236.6 | ... L107: =L104+L106 -> -8332236.6
B108: (–) Intereses | C108: =-D168 -> -313065.37 | D108: =-E168 -> -260887.81 | E108: =-F168 -> -208710.24 | F108: =-G168 -> -156532.68 | G108: =-H168 -> -104355.12 | H108: =-I168 -> -52177.561 | I108: =-J168 -> 0 | J108: =-K168 -> 0 | ... L108: =-M168 -> 0
B109: EBT | C109: =C107+C108 -> -4573373.7 | D109: =D107+D108 -> -6557160.3 | E109: =E107+E108 -> -8540946.9 | F109: =F107+F108 -> -8488769.3 | G109: =G107+G108 -> -8436591.7 | H109: =H107+H108 -> -8384414.2 | I109: =I107+I108 -> -8332236.6 | J109: =J107+J108 -> -8332236.6 | ... L109: =L107+L108 -> -8332236.6
B110: (–) ISR 30% | C110: =-MAX(0,C109)*C15 -> 0 | D110: =-MAX(0,D109)*C15 -> 0 | E110: =-MAX(0,E109)*C15 -> 0 | F110: =-MAX(0,F109)*C15 -> 0 | G110: =-MAX(0,G109)*C15 -> 0 | H110: =-MAX(0,H109)*C15 -> 0 | I110: =-MAX(0,I109)*C15 -> 0 | J110: =-MAX(0,J109)*C15 -> 0 | K110: =-MAX(0,K109)*C15 -> 0 | L110: =-MAX(0,L109)*C15 -> 0
B111: (–) PTU 10% | C111: =-MAX(0,C109)*C16 -> 0 | D111: =-MAX(0,D109)*C16 -> 0 | E111: =-MAX(0,E109)*C16 -> 0 | F111: =-MAX(0,F109)*C16 -> 0 | G111: =-MAX(0,G109)*C16 -> 0 | H111: =-MAX(0,H109)*C16 -> 0 | I111: =-MAX(0,I109)*C16 -> 0 | J111: =-MAX(0,J109)*C16 -> 0 | K111: =-MAX(0,K109)*C16 -> 0 | L111: =-MAX(0,L109)*C16 -> 0
B112: Utilidad neta | C112: =C109+C110+C111 -> -4573373.7 | D112: =D109+D110+D111 -> -6557160.3 | E112: =E109+E110+E111 -> -8540946.9 | F112: =F109+F110+F111 -> -8488769.3 | G112: =G109+G110+G111 -> -8436591.7 | H112: =H109+H110+H111 -> -8384414.2 | I112: =I109+I110+I111 -> -8332236.6 | J112: =J109+J110+J111 -> -8332236.6 | ... L112: =L109+L110+L111 -> -8332236.6
B113: (–) Reserva legal 5% | C113: =-MAX(0,C112)*C17 -> 0 | D113: =-MAX(0,D112)*C17 -> 0 | E113: =-MAX(0,E112)*C17 -> 0 | F113: =-MAX(0,F112)*C17 -> 0 | G113: =-MAX(0,G112)*C17 -> 0 | H113: =-MAX(0,H112)*C17 -> 0 | I113: =-MAX(0,I112)*C17 -> 0 | J113: =-MAX(0,J112)*C17 -> 0 | K113: =-MAX(0,K112)*C17 -> 0 | L113: =-MAX(0,L112)*C17 -> 0
...

Sheet Vidrio
B2: BLOQUE A — SUPUESTOS PARAMETRIZADOS — VIDRIO
B3: Parámetro | C3: Valor | D3: Unidad | E3: Fuente / Nota
B4: Tipo de cambio USD/MXN | C4: 17.1 | D4: MXN/USD
B5: Tarifa eléctrica industrial SLP | C5: 3 | D5: MXN/kWh | E5: Ref CFE tarifa GDMTH SLP
B6: Precio gas LP industrial | C6: 18.5 | D6: MXN/kg | E6: Supuesto razonado
B7: Precio diésel | C7: 26 | D7: MXN/litro | E7: Supuesto razonado
B8: Factor contingencia energética | C8: 1.1 | D8: x
B9: Días operativos/año | C9: 300 | D9: días
B10: Días operativos/mes | C10: 25 | D10: días
B11: Merma estimada | C11: 0.1 | D11: %
B12: Renta zona industrial | C12: 65 | D12: MXN/m²/mes
B13: Factor prestaciones sociales | C13: 1.35 | D13: x
B14: WACC | C14: 0.2 | D14: %
B15: ISR | C15: 0.3 | D15: %
B16: PTU | C16: 0.1 | D16: %
B17: Reserva legal | C17: 0.05 | D17: %
B18: Vida útil maquinaria industrial | C18: 10 | D18: años
B19: Vida útil transporte | C19: 4 | D19: años
... B27: DPO (días cuentas por pagar) | C27: 15 | D27: días
B28: Múltiplo valor terminal EBITDA | C28: 5 | D28: x | E28: Rango 4-6x
B29: Estructura D/E (% deuda) | C29: 0.6 | D29: % | E29: 60/40
B30: Tasa interés deuda | C30: 0.135 | D30: % anual
B31: Plazo deuda | C31: 6 | D31: años
B33: Parámetros específicos — Vidrio
B34: Volumen entrada t/mes | C34: 907.2 | D34: t/mes | E34: Supuesto razonado
B35: Escenario % procesado 30% | C35: 0.3 | D35: % | E35: 30%=municipio
B36: Escenario % procesado 40% | C36: 0.4 | D36: % | E36: 40%=concesionario
B37: Escenario % procesado 80% | C37: 0.8 | D37: % | E37: 80%=fondos de impacto
B38: Rendimiento proceso kg/kg entrada | C38: 0.92 | D38: kg/kg
B39: Precio cullet transparente | C39: 4.5 | D39: MXN/kg
B40: Precio cullet verde | C40: 2.8 | D40: MXN/kg
B41: Precio cullet ámbar | C41: 3.2 | D41: MXN/kg
B42: Precio compra MP centros de acopio (Vidrio) | C42: 2.5 | D42: MXN/kg
B43: Precio procesado promedio ponderado | C43: 3.83 | D43: MXN/kg | E43: 40%×$4.50+35%×$3.20+25%×$2.80
B44: Nave industrial m² | C44: 300 | D44: m²
B45: Nómina mensual (6 operarios + 1 supervisor) | C45: 104625 | D45: MXN/mes | E45: (6*10000+1*17500)*1.35
B46: Compradores ancla | C46: Vidriera Monterrey (OWENS-ILLINOIS), Vitro, Grupo Altsa | E46: Pureza mínima 98% por color, máx 0.5% metales
B47: Transporte/combustible mensual | C47: 15000 | D47: MXN/mes | E47: Supuesto operativo
B48: Agua y servicios mensual | C48: 3000 | D48: MXN/mes | E48: Supuesto operativo
B49: BLOQUE B — CAPEX CON CONSUMOS ENERGÉTICOS — VIDRIO
B50: Equipo | C50: Marca/Modelo | D50: Cant | E50: Precio unit MXN | F50: Total MXN | G50: kW nominal | H50: Factor util% | I50: Horas efect/día | J50: Días/mes | K50: kWh/mes | L50: kWh×1.10 | M50: Costo MXN/mes | N50: Nota
B51: Molino de vidrio 2t/h | C51: Genérico nacional | D51: 1 | E51: 320000 | F51: =D51*E51 -> 320000 | G51: 30 | H51: 0.75 | I51: =H51*8 -> 6 | J51: =C10 -> 25 | K51: =G51*I51*J51*D51 -> 4500 | L51: =K51*C8 -> 4950 | M51: =L51*C5 -> 14850
B52: Separador por color (banda óptica) | C52: Genérico/importado | D52: 1 | E52: 580000 | F52: =D52*E52 -> 580000 | G52: 5 | H52: 0.7 | I52: =H52*8 -> 5.6 | J52: =C10 -> 25 | K52: =G52*I52*J52*D52 -> 700 | L52: =K52*C8 -> 770 | M52: =L52*C5 -> 2310
B53: Banda transportadora 8m | C53: Nacional | D53: 2 | E53: 45000 | F53: =D53*E53 -> 90000 | G53: 2.2 | H53: 0.8 | I53: =H53*8 -> 6.4 | J53: =C10 -> 25 | K53: =G53*I53*J53*D53 -> 704 | L53: =K53*C8 -> 774.4 | M53: =L53*C5 -> 2323.2
B54: Báscula 1,000kg | C54: Torrey | D54: 1 | E54: 10000 | F54: =D54*E54 -> 10000 | G54: 0.1 | H54: 0.4 | I54: =H54*8 -> 3.2 | J54: =C10 -> 25 | K54: =G54*I54*J54*D54 -> 8 | L54: =K54*C8 -> 8.8 | M54: =L54*C5 -> 26.4
B55: Herramienta menor + EPI vidrio | C55: Varios | D55: 1 | E55: 35000 | F55: =D55*E55 -> 35000 | G55: 0 | K55: 0 | L55: =K55*C8 -> 0 | M55: =L55*C5 -> 0
B56: TOTAL EQUIPAMIENTO | F56: =SUM(F51:F55) -> 1035000 | K56: =SUM(K51:K55) -> 5912 | L56: =SUM(L51:L55) -> 6503.2 | M56: =SUM(M51:M55) -> 19509.6
B58: BLOQUE C — CAPEX TOTAL — VIDRIO
B59: Concepto | C59: Monto MXN
B60: Equipamiento | C60: =F56 -> 1035000
B61: Adecuación de nave | C61: 220000
B62: Gastos preoperativos | C62: 55000
B63: Capital de trabajo (2 meses OPEX) | C63: =(C79-C68)*2 -> 562563.94
B64: CAPEX TOTAL | C64: =SUM(C60:C63) -> 1872563.9
B66: BLOQUE D — OPEX MENSUAL — VIDRIO
B67: Concepto | C67: MXN/mes
B68: CMV — Compra MP en centros de acopio (Vidrio) | C68: =C34*C36*(1-C11)*C42*1000 -> 816480
B69: Renta | C69: =C44*C12 -> 19500
B70: Energía eléctrica | C70: =M56 -> 19509.6
B71: Nómina con prestaciones | C71: =C45 -> 104625
B72: Transporte/combustible | C72: =$C$47 -> 15000
B73: Mantenimiento equipo (2.5% CAPEX/12) | C73: =C60*0.025/12 -> 2156.25
B74: Insumos (agua proceso, empaques, químicos) | C74: =E93*0.03 -> 28505.995
B75: Agua y servicios | C75: =$C$48 -> 3000
B76: Seguros (0.5% CAPEX total / 12) | C76: =(C60+C61)*0.005/12 -> 522.91667
B77: Flete a comprador (8% ingreso 40%) | C77: =E91*8/100 -> 84462.207
B78: Consumibles de línea (cuchillas, filtros, bandas, refacciones) | C78: 4000
B79: TOTAL OPEX MENSUAL | C79: =SUM(C68:C78) -> 1097762
B80: Nota analítica: RIESGO PRINCIPAL: Vidrio es el material de menor ingreso/kg. La rentabilidad depende del volumen y la separación correcta por color. Vidrio mixto no separado: $2.50/kg vs cullet transparente: $4.50/kg (diferencia 80%). Depende de calidad del centro de acopio.
B82: BLOQUE E — INGRESOS MENSUALES POR ESCENARIO — VIDRIO
B83: Concepto | C83: Unidad | D83: Esc 30% | E83: Esc 40% | F83: Esc 80%
B84: Volumen entrada t/mes | C84: t/mes | D84: =$C$34*C35 -> 272.16 | E84: =$C$34*C36 -> 362.88 | F84: =$C$34*C37 -> 725.76
B85: Volumen procesado internamente t/mes | C85: t/mes | D85: =D84*C35 -> 81.648 | E85: =E84*C36 -> 145.152 | F85: =F84*C37 -> 580.608
B86: Precio producto procesado MXN/kg | C86: MXN/kg | D86: =C43 -> 3.83 | E86: =C43 -> 3.83 | F86: =C43 -> 3.83
B87: Ingreso por material procesado | C87: MXN/mes | D87: =D85*1000*C38*D86 -> 287694.89 | E87: =E85*1000*C38*E86 -> 511457.59 | F87: =F85*1000*C38*F86 -> 2045830.3
B88: Volumen comercializado t/mes | C88: t/mes | D88: =D84*(1-C35) -> 190.512 | E88: =E84*(1-C36) -> 217.728 | F88: =F84*(1-C37) -> 145.152
B89: Precio comercialización MXN/kg | C89: MXN/kg | D89: =C42 -> 2.5 | E89: =C42 -> 2.5 | F89: =C42 -> 2.5
B90: Ingreso por comercialización | C90: MXN/mes | D90: =D88*1000*D89 -> 476280 | E90: =E88*1000*E89 -> 544320 | F90: =F88*1000*F89 -> 362880
B91: INGRESO TOTAL MENSUAL | C91: MXN/mes | D91: =D87+D90 -> 763974.89 | E91: =E87+E90 -> 1055777.6 | F91: =F87+F90 -> 2408710.3
B92: (–) Merma 10% | C92: MXN/mes | D92: =-D91*C11 -> -76397.489 | E92: =-E91*C11 -> -105577.76 | F92: =-F91*C11 -> -240871.03
B93: INGRESO NETO MENSUAL | C93: MXN/mes | D93: =D91+D92 -> 687577.4 | E93: =E91+E92 -> 950199.83 | F93: =F91+F92 -> 2167839.3
B94: Precios de referencia marzo 2026. Sujetos a revisión trimestral con base en índices ANIPAC, CEMPRE México y cotizaciones directas de compradores ancla.
B96: BLOQUE F — ESTADO DE RESULTADOS P&L (Año 1 a Año 10) — VIDRIO
B97: P&L — Esc 30% (30% procesado)
B98: Concepto | C98: Año 1 | D98: Año 2 | E98: Año 3 | F98: Año 4 | G98: Año 5 | H98: Año 6 | I98: Año 7 | J98: Año 8 | K98: Año 9 | L98: Año 10
B99: Ingresos brutos | C99: =D91*12*C22 -> 4583849.4 | D99: =D91*12*C23 -> 6875774 | E99: =D91*12*C24 -> 9167698.7 | F99: =D91*12*C24 -> 9167698.7 | G99: =D91*12*C24 -> 9167698.7 | H99: =D91*12*C24 -> 9167698.7 | I99: =D91*12*C24 -> 9167698.7 | J99: =D91*12*C24 -> 9167698.7 | K99: =D91*12*C24 -> 9167698.7 | L99: =D91*12*C24 -> 9167698.7
B100: (–) Merma 10% | C100: =-C99*C11 -> -458384.94 | D100: =-D99*C11 -> -687577.4 | E100: =-E99*C11 -> -916769.87 | F100: =-F99*C11 -> -916769.87 | G100: =-G99*C11 -> -916769.87 | H100: =-H99*C11 -> -916769.87 | I100: =-I99*C11 -> -916769.87 | J100: =-J99*C11 -> -916769.87 | K100: =-K99*C11 -> -916769.87 | L100: =-L99*C11 -> -916769.87
B101: Ingresos netos | C101: =C99+C100 -> 4125464.4 | D101: =D99+D100 -> 6188196.6 | E101: =E99+E100 -> 8250928.8 | F101: =F99+F100 -> 8250928.8 | G101: =G99+G100 -> 8250928.8 | H101: =H99+H100 -> 8250928.8 | I101: =I99+I100 -> 8250928.8 | J101: =J99+J100 -> 8250928.8 | ... L101: =L99+L100 -> 8250928.8
B102: (–) OPEX total | C102: =-C79*12*C22 -> -6586571.8 | D102: =-C79*12*C23 -> -9879857.7 | E102: =-C79*12*C24 -> -13173144 | F102: =-C79*12*C24 -> -13173144 | G102: =-C79*12*C24 -> -13173144 | H102: =-C79*12*C24 -> -13173144 | I102: =-C79*12*C24 -> -13173144 | J102: =-C79*12*C24 -> -13173144 | K102: =-C79*12*C24 -> -13173144 | L102: =-C79*12*C24 -> -13173144
B103: EBITDA | C103: =C101+C102 -> -2461107.4 | D103: =D101+D102 -> -3691661.1 | E103: =E101+E102 -> -4922214.8 | F103: =F101+F102 -> -4922214.8 | G103: =G101+G102 -> -4922214.8 | H103: =H101+H102 -> -4922214.8 | I103: =I101+I102 -> -4922214.8 | J103: =J101+J102 -> -4922214.8 | ... L103: =L101+L102 -> -4922214.8
B104: Margen EBITDA % | C104: =IF(C101=0,0,C103/C101) -> -0.59656493 | D104: =IF(D101=0,0,D103/D101) -> -0.59656493 | E104: =IF(E101=0,0,E103/E101) -> -0.59656493 | F104: =IF(F101=0,0,F103/F101) -> -0.59656493 | G104: =IF(G101=0,0,G103/G101) -> -0.59656493 | H104: =IF(H101=0,0,H103/H101) -> -0.59656493 | I104: =IF(I101=0,0,I103/I101) -> -0.59656493 | J104: =IF(J101=0,0,J103/J101) -> -0.59656493 | ... L104: =IF(L101=0,0,L103/L101) -> -0.59656493
B105: (–) Depreciación y amortización | C105: =-(C60/C18+C61/20) -> -114500 | D105: =-(C60/C18+C61/20) -> -114500 | E105: =-(C60/C18+C61/20) -> -114500 | F105: =-(C60/C18+C61/20) -> -114500 | G105: =-(C60/C18+C61/20) -> -114500 | H105: =-(C60/C18+C61/20) -> -114500 | I105: =-(C60/C18+C61/20) -> -114500 | J105: =-(C60/C18+C61/20) -> -114500 | K105: =-(C60/C18+C61/20) -> -114500 | L105: =-(C60/C18+C61/20) -> -114500
B106: EBIT | C106: =C103+C105 -> -2575607.4 | D106: =D103+D105 -> -3806161.1 | E106: =E103+E105 -> -5036714.8 | F106: =F103+F105 -> -5036714.8 | G106: =G103+G105 -> -5036714.8 | H106: =H103+H105 -> -5036714.8 | I106: =I103+I105 -> -5036714.8 | J106: =J103+J105 -> -5036714.8 | ... L106: =L103+L105 -> -5036714.8
B107: (–) Intereses | C107: =-D167 -> -151677.68 | D107: =-E167 -> -126398.07 | E107: =-F167 -> -101118.45 | F107: =-G167 -> -75838.839 | G107: =-H167 -> -50559.226 | H107: =-I167 -> -25279.613 | I107: =-J167 -> 0 | J107: =-K167 -> 0 | ... L107: =-M167 -> 0
B108: EBT | C108: =C106+C107 -> -2727285.1 | D108: =D106+D107 -> -3932559.2 | E108: =E106+E107 -> -5137833.2 | F108: =F106+F107 -> -5112553.6 | G108: =G106+G107 -> -5087274 | H108: =H106+H107 -> -5061994.4 | I108: =I106+I107 -> -5036714.8 | J108: =J106+J107 -> -5036714.8 | ... L108: =L106+L107 -> -5036714.8
B109: (–) ISR 30% | C109: =-MAX(0,C108)*C15 -> 0 | D109: =-MAX(0,D108)*C15 -> 0 | E109: =-MAX(0,E108)*C15 -> 0 | F109: =-MAX(0,F108)*C15 -> 0 | G109: =-MAX(0,G108)*C15 -> 0 | H109: =-MAX(0,H108)*C15 -> 0 | I109: =-MAX(0,I108)*C15 -> 0 | J109: =-MAX(0,J108)*C15 -> 0 | K109: =-MAX(0,K108)*C15 -> 0 | L109: =-MAX(0,L108)*C15 -> 0
B110: (–) PTU 10% | C110: =-MAX(0,C108)*C16 -> 0 | D110: =-MAX(0,D108)*C16 -> 0 | E110: =-MAX(0,E108)*C16 -> 0 | F110: =-MAX(0,F108)*C16 -> 0 | G110: =-MAX(0,G108)*C16 -> 0 | H110: =-MAX(0,H108)*C16 -> 0 | I110: =-MAX(0,I108)*C16 -> 0 | J110: =-MAX(0,J108)*C16 -> 0 | K110: =-MAX(0,K108)*C16 -> 0 | L110: =-MAX(0,L108)*C16 -> 0
B111: Utilidad neta | C111: =C108+C109+C110 -> -2727285.1 | D111: =D108+D109+D110 -> -3932559.2 | E111: =E108+E109+E110 -> -5137833.2 | F111: =F108+F109+F110 -> -5112553.6 | G111: =G108+G109+G110 -> -5087274 | H111: =H108+H109+H110 -> -5061994.4 | I111: =I108+I109+I110 -> -5036714.8 | J111: =J108+J109+J110 -> -5036714.8 | ... L111: =L108+L109+L110 -> -5036714.8
B112: (–) Reserva legal 5% | C112: =-MAX(0,C111)*C17 -> 0 | D112: =-MAX(0,D111)*C17 -> 0 | E112: =-MAX(0,E111)*C17 -> 0 | F112: =-MAX(0,F111)*C17 -> 0 | G112: =-MAX(0,G111)*C17 -> 0 | H112: =-MAX(0,H111)*C17 -> 0 | I112: =-MAX(0,I111)*C17 -> 0 | J112: =-MAX(0,J111)*C17 -> 0 | K112: =-MAX(0,K111)*C17 -> 0 | L112: =-MAX(0,L111)*C17 -> 0
B113: Utilidad distribuible | C113: =C111+C112 -> -2727285.1 | D113: =D111+D112 -> -3932559.2 | E113: =E111+E112 -> -5137833.2 | F113: =F111+F112 -> -5112553.6 | G113: =G111+G112 -> -5087274 | H113: =H111+H112 -> -5061994.4 | I113: =I111+I112 -> -5036714.8 | J113: =J111+J112 -> -5036714.8 | ... L113: =L111+L112 -> -5036714.8
...

Sheet Organicos-Composta
B2: BLOQUE A — SUPUESTOS PARAMETRIZADOS — ORGANICOS-COMPOSTA
B3: Parámetro | C3: Valor | D3: Unidad | E3: Fuente / Nota
B4: Tipo de cambio USD/MXN | C4: 17.1 | D4: MXN/USD
B5: Tarifa eléctrica industrial SLP | C5: 3 | D5: MXN/kWh | E5: Ref CFE tarifa GDMTH SLP
B6: Precio gas LP industrial | C6: 18.5 | D6: MXN/kg | E6: Supuesto razonado
B7: Precio diésel | C7: 26 | D7: MXN/litro | E7: Supuesto razonado
B8: Factor contingencia energética | C8: 1.1 | D8: x
B9: Días operativos/año | C9: 300 | D9: días
B10: Días operativos/mes | C10: 25 | D10: días
B11: Merma estimada | C11: 0.1 | D11: %
B12: Renta zona industrial | C12: 65 | D12: MXN/m²/mes
B13: Factor prestaciones sociales | C13: 1.35 | D13: x
B14: WACC | C14: 0.2 | D14: %
B15: ISR | C15: 0.3 | D15: %
B16: PTU | C16: 0.1 | D16: %
B17: Reserva legal | C17: 0.05 | D17: %
B18: Vida útil maquinaria industrial | C18: 10 | D18: años
B19: Vida útil transporte | C19: 4 | D19: años
... B27: DPO (días cuentas por pagar) | C27: 15 | D27: días
B28: Múltiplo valor terminal EBITDA | C28: 5 | D28: x | E28: Rango 4-6x
B29: Estructura D/E (% deuda) | C29: 0.6 | D29: % | E29: 60/40
B30: Tasa interés deuda | C30: 0.135 | D30: % anual
B31: Plazo deuda | C31: 6 | D31: años
B33: Parámetros específicos — Organicos-Composta
B34: Volumen entrada t/mes | C34: 362 | D34: t/mes | E34: Supuesto razonado
B35: Escenario % procesado 30% | C35: 0.3 | D35: % | E35: 30%=municipio
B36: Escenario % procesado 40% | C36: 0.4 | D36: % | E36: 40%=concesionario
B37: Escenario % procesado 80% | C37: 0.8 | D37: % | E37: 80%=fondos de impacto
B38: Rendimiento composta kg/kg entrada | C38: 0.4 | D38: kg/kg | E38: Pérdida humedad en proceso
B39: Precio bolsa 5kg | C39: 45 | D39: MXN/bolsa
B40: Precio bolsa 20kg | C40: 120 | D40: MXN/bolsa
B41: Precio bulto 50kg | C41: 220 | D41: MXN/bulto
B42: Precio compra MP centros de acopio (Orgánicos) | C42: 1 | D42: MXN/kg | E42: Precio compra orgánicos en centros de acopio
B43: Precio orgánico a granel | C43: 1 | D43: MXN/kg | E43: Precio venta a granel agricultura. Ref. mercado SLP 0.80-1.20/kg a granel, 1.50-4.00/kg ensacado retail. Vigencia abr-2026. Revisar trimestralmente con compradores locales (viveros, huertas, proyectos agroecológicos).
B44: Mix ventas 5kg | C44: 0.4 | D44: %
B45: Mix ventas 20kg | C45: 0.35 | D45: %
B46: Mix ventas 50kg | C46: 0.25 | D46: %
B47: Capital de trabajo | C47: 3 | D47: meses OPEX | E47: Proceso 60-90 días
B48: Nave industrial m² | C48: 400 | D48: m²
B49: Nómina mensual ( 10 operarios + 1 supervisor + 1 técnico agronómico) | C49: 186975 | D49: MXN/mes | E49: (10*10000+1*17500+1*20000)*1.35
B50: Compradores ancla | C50: Viveros SLP 40%, ferreterías 30%, autoservicio 20%, agricultores 10% | E50: Mix ventas: 40% bolsas 5kg ($45), 35% bolsas 20kg ($120), 25% bultos 50kg ($220)
B51: Transporte/combustible mensual | C51: 20000 | D51: MXN/mes | E51: Supuesto operativo
B52: Agua y servicios mensual | C52: 6000 | D52: MXN/mes | E52: Supuesto operativo (incl. agua para compostaje)
B53: BLOQUE B — CAPEX CON CONSUMOS ENERGÉTICOS — ORGANICOS-COMPOSTA
B54: Equipo | C54: Marca/Modelo | D54: Cant | E54: Precio unit MXN | F54: Total MXN | G54: kW nominal | H54: Factor util% | I54: Horas efect/día | J54: Días/mes | K54: kWh/mes | L54: kWh×1.10 | M54: Costo MXN/mes | N54: Nota
B55: Biodigestor 25m³/día | C55: Nacional/Importado | D55: 1 | E55: 850000 | F55: =D55*E55 -> 850000 | G55: 15 | H55: 0.6 | I55: =H55*8 -> 4.8 | J55: =C10 -> 25 | K55: =G55*I55*J55*D55 -> 1800 | L55: =K55*C8 -> 1980 | M55: =L55*C5 -> 5940 | N55: Genera biogás ~$0.20/kWh equiv
B56: Volteo composta mecánico (trommel) 10t/h | C56: Nacional | D56: 1 | E56: 380000 | F56: =D56*E56 -> 380000 | G56: 22 | H56: 0.5 | I56: =H56*8 -> 4 | J56: =C10 -> 25 | K56: =G56*I56*J56*D56 -> 2200 | L56: =K56*C8 -> 2420 | M56: =L56*C5 -> 7260
B57: Tamizadora vibratoria | C57: Nacional | D57: 1 | E57: 180000 | F57: =D57*E57 -> 180000 | G57: 7.5 | H57: 0.6 | I57: =H57*8 -> 4.8 | J57: =C10 -> 25 | K57: =G57*I57*J57*D57 -> 900 | L57: =K57*C8 -> 990 | M57: =L57*C5 -> 2970
B58: Ensacadora semiautomática | C58: Nacional | D58: 1 | E58: 280000 | F58: =D58*E58 -> 280000 | G58: 5 | H58: 0.7 | I58: =H58*8 -> 5.6 | J58: =C10 -> 25 | K58: =G58*I58*J58*D58 -> 700 | L58: =K58*C8 -> 770 | M58: =L58*C5 -> 2310
B59: Báscula 500kg | C59: Rhino | D59: 1 | E59: 3800 | F59: =D59*E59 -> 3800 | G59: 0.1 | H59: 0.4 | I59: =H59*8 -> 3.2 | J59: =C10 -> 25 | K59: =G59*I59*J59*D59 -> 8 | L59: =K59*C8 -> 8.8 | M59: =L59*C5 -> 26.4
B60: Herramienta menor + equipo volteo | C60: Varios | D60: 1 | E60: 45000 | F60: =D60*E60 -> 45000 | G60: 0 | K60: 0 | L60: =K60*C8 -> 0 | M60: =L60*C5 -> 0
B61: TOTAL EQUIPAMIENTO | F61: =SUM(F55:F60) -> 1738800 | K61: =SUM(K55:K60) -> 5608 | L61: =SUM(L55:L60) -> 6168.8 | M61: =SUM(M55:M60) -> 18506.4
B63: BLOQUE C — CAPEX TOTAL — ORGANICOS-COMPOSTA
B64: Concepto | C64: Monto MXN
B65: Equipamiento | C65: =F61 -> 1738800
B66: Adecuación de nave | C66: 420000
B67: Gastos preoperativos | C67: 55000
B68: Capital de trabajo (3 meses OPEX) | C68: =(C84-C73)*3 -> 991159.18
B69: CAPEX TOTAL | C69: =SUM(C65:C68) -> 3204959.2
B71: BLOQUE D — OPEX MENSUAL — ORGANICOS-COMPOSTA
B72: Concepto | C72: MXN/mes
B73: CMV — Compra MP en centros de acopio (Orgánicos) | C73: =C34*C36*(1-C11)*C42*1000 -> 130320
B74: Renta | C74: =C48*C12 -> 26000
B75: Energía eléctrica | C75: =M61 -> 18506.4
B76: Nómina con prestaciones | C76: =C49 -> 186975
B77: Transporte/combustible | C77: =$C$51 -> 20000
B78: Mantenimiento equipo (2.5% CAPEX/12) | C78: =C65*0.025/12 -> 3622.5
B79: Insumos (agua proceso, empaques, químicos) | C79: =E102*0.03 -> 16498.512
B80: Agua y servicios | C80: =$C$52 -> 6000
B81: Seguros (0.5% CAPEX total / 12) | C81: =(C65+C66)*0.005/12 -> 899.5
B82: Flete a comprador (8% ingreso 40%) | C82: =E100*0.08 -> 48884.48
B83: Consumibles de línea (cuchillas, filtros, bandas, refacciones) | C83: 3000
B84: TOTAL OPEX MENSUAL | C84: =SUM(C73:C83) -> 460706.39
B87: BLOQUE E — INGRESOS MENSUALES POR ESCENARIO — ORGANICOS-COMPOSTA
B88: Concepto | C88: Unidad | D88: Esc 30% | E88: Esc 40% | F88: Esc 80%
B89: Volumen entrada t/mes | C89: t/mes | D89: =C34 -> 362 | E89: =C34 -> 362 | F89: =C34 -> 362
B90: Volumen procesado internamente t/mes | C90: t/mes | D90: =D89*C35 -> 108.6 | E90: =E89*C36 -> 144.8 | F90: =F89*C37 -> 289.6
B91: Composta producida t/mes | C91: t/mes | D91: =D90*C38 -> 43.44 | E91: =E90*C38 -> 57.92 | F91: =F90*C38 -> 115.84
B92: Composta producida kg/mes | C92: kg/mes | D92: =D91*1000 -> 43440 | E92: =E91*1000 -> 57920 | F92: =F91*1000 -> 115840
B93: Ingreso bolsas 5kg (40% mix) | C93: MXN/mes | D93: =D92*C44/5*C39 -> 156384 | E93: =E92*C44/5*C39 -> 208512 | F93: =F92*C44/5*C39 -> 417024
B94: Ingreso bolsas 20kg (35% mix) | C94: MXN/mes | D94: =D92*C45/20*C40 -> 91224 | E94: =E92*C45/20*C40 -> 121632 | F94: =F92*C45/20*C40 -> 243264
B95: Ingreso bultos 50kg (25% mix) | C95: MXN/mes | D95: =D92*C46/50*C41 -> 47784 | E95: =E92*C46/50*C41 -> 63712 | F95: =F92*C46/50*C41 -> 127424
B96: Ingreso por material procesado (bolsas) | C96: MXN/mes | D96: =D93+D94+D95 -> 295392 | E96: =E93+E94+E95 -> 393856 | F96: =F93+F94+F95 -> 787712
B97: Volumen comercializado t/mes | C97: t/mes | D97: =D89*(1-C35) -> 253.4 | E97: =E89*(1-C36) -> 217.2 | F97: =F89*(1-C37) -> 72.4
B98: Precio comercialización MXN/kg | C98: MXN/kg | D98: =C43 -> 1 | E98: =C43 -> 1 | F98: =C43 -> 1
B99: Ingreso por comercialización | C99: MXN/mes | D99: =D97*1000*D98 -> 253400 | E99: =E97*1000*E98 -> 217200 | F99: =F97*1000*F98 -> 72400
B100: INGRESO TOTAL MENSUAL | C100: MXN/mes | D100: =D96+D99 -> 548792 | E100: =E96+E99 -> 611056 | F100: =F96+F99 -> 860112
B101: (–) Merma 10% | C101: MXN/mes | D101: =-D100*C11 -> -54879.2 | E101: =-E100*C11 -> -61105.6 | F101: =-F100*C11 -> -86011.2
B102: INGRESO NETO MENSUAL | C102: MXN/mes | D102: =D100+D101 -> 493912.8 | E102: =E100+E101 -> 549950.4 | F102: =F100+F101 -> 774100.8
B103: Precios de referencia marzo 2026. Sujetos a revisión trimestral con base en índices ANIPAC, CEMPRE México y cotizaciones directas de compradores ancla.
B105: BLOQUE F — ESTADO DE RESULTADOS P&L (Año 1 a Año 10) — ORGANICOS-COMPOSTA
B106: P&L — Esc 30% (30% procesado)
B107: Concepto | C107: Año 1 | D107: Año 2 | E107: Año 3 | F107: Año 4 | G107: Año 5 | H107: Año 6 | I107: Año 7 | J107: Año 8 | K107: Año 9 | L107: Año 10
B108: Ingresos brutos | C108: =D100*12*C22 -> 3292752 | D108: =D100*12*C23 -> 4939128 | E108: =D100*12*C24 -> 6585504 | F108: =D100*12*C24 -> 6585504 | G108: =D100*12*C24 -> 6585504 | H108: =D100*12*C24 -> 6585504 | I108: =D100*12*C24 -> 6585504 | J108: =D100*12*C24 -> 6585504 | K108: =D100*12*C24 -> 6585504 | L108: =D100*12*C24 -> 6585504
B109: (–) Merma 10% | C109: =-C108*C11 -> -329275.2 | D109: =-D108*C11 -> -493912.8 | E109: =-E108*C11 -> -658550.4 | F109: =-F108*C11 -> -658550.4 | G109: =-G108*C11 -> -658550.4 | H109: =-H108*C11 -> -658550.4 | I109: =-I108*C11 -> -658550.4 | J109: =-J108*C11 -> -658550.4 | K109: =-K108*C11 -> -658550.4 | L109: =-L108*C11 -> -658550.4
B110: Ingresos netos | C110: =C108+C109 -> 2963476.8 | D110: =D108+D109 -> 4445215.2 | E110: =E108+E109 -> 5926953.6 | F110: =F108+F109 -> 5926953.6 | G110: =G108+G109 -> 5926953.6 | H110: =H108+H109 -> 5926953.6 | I110: =I108+I109 -> 5926953.6 | J110: =J108+J109 -> 5926953.6 | ... L110: =L108+L109 -> 5926953.6
B111: (–) OPEX total | C111: =-C84*12*C22 -> -2764238.4 | D111: =-C84*12*C23 -> -4146357.5 | E111: =-C84*12*C24 -> -5528476.7 | F111: =-C84*12*C24 -> -5528476.7 | G111: =-C84*12*C24 -> -5528476.7 | H111: =-C84*12*C24 -> -5528476.7 | I111: =-C84*12*C24 -> -5528476.7 | J111: =-C84*12*C24 -> -5528476.7 | K111: =-C84*12*C24 -> -5528476.7 | L111: =-C84*12*C24 -> -5528476.7
B112: EBITDA | C112: =C110+C111 -> 199238.45 | D112: =D110+D111 -> 298857.67 | E112: =E110+E111 -> 398476.9 | F112: =F110+F111 -> 398476.9 | G112: =G110+G111 -> 398476.9 | H112: =H110+H111 -> 398476.9 | I112: =I110+I111 -> 398476.9 | J112: =J110+J111 -> 398476.9 | ... L112: =L110+L111 -> 398476.9
B113: Margen EBITDA % | C113: =IF(C110=0,0,C112/C110) -> 0.067231317 | D113: =IF(D110=0,0,D112/D110) -> 0.067231317 | E113: =IF(E110=0,0,E112/E110) -> 0.067231317 | F113: =IF(F110=0,0,F112/F110) -> 0.067231317 | G113: =IF(G110=0,0,G112/G110) -> 0.067231317 | H113: =IF(H110=0,0,H112/H110) -> 0.067231317 | I113: =IF(I110=0,0,I112/I110) -> 0.067231317 | J113: =IF(J110=0,0,J112/J110) -> 0.067231317 | ... L113: =IF(L110=0,0,L112/L110) -> 0.067231317
B114: (–) Depreciación y amortización | C114: =-(C65/C18+C66/20) -> -194880 | D114: =-(C65/C18+C66/20) -> -194880 | E114: =-(C65/C18+C66/20) -> -194880 | F114: =-(C65/C18+C66/20) -> -194880 | G114: =-(C65/C18+C66/20) -> -194880 | H114: =-(C65/C18+C66/20) -> -194880 | I114: =-(C65/C18+C66/20) -> -194880 | J114: =-(C65/C18+C66/20) -> -194880 | K114: =-(C65/C18+C66/20) -> -194880 | L114: =-(C65/C18+C66/20) -> -194880
...
